testbench/program.v
`define NUM_INSTRUCTIONS 130

task program(); begin
	#10 instr = 16'hA064;
	#10 instr = 16'hA428;
	#10 instr = 16'h9400;
	#10 instr = 16'hA432;
	#10 instr = 16'h9402;
	#10 instr = 16'hA41E;
	#10 instr = 16'h9404;
	#10 instr = 16'hA432;
	#10 instr = 16'h9406;
	#10 instr = 16'hA41E;
	#10 instr = 16'h9408;
	#10 instr = 16'hA428;
	#10 instr = 16'h940A;
	#10 instr = 16'hA804;
	#10 instr = 16'hAC1E;
	#10 instr = 16'h8400;
	#10 instr = 16'h2502;
	#10 instr = 16'h1503;
	#10 instr = 16'h940C;
	#10 instr = 16'h0002;
	#10 instr = 16'hDC70;
	#10 instr = 16'hDF01;
	#10 instr = 16'hEEEC;
	#10 instr = 16'hA400;
	#10 instr = 16'h8800;
	#10 instr = 16'h1502;
	#10 instr = 16'h0002;
	#10 instr = 16'hDC7C;
	#10 instr = 16'hDF01;
	#10 instr = 16'hA800;
	#10 instr = 16'hEEF4;
	#10 instr = 16'hA801;
	#10 instr = 16'h3502;
	#10 instr = 16'hA802;
	#10 instr = 16'h3102;
	#10 instr = 16'hA804;
	#10 instr = 16'h3D02;
	#10 instr = 16'hA806;
	#10 instr = 16'h3502;
	#10 instr = 16'h1503;
	#10 instr = 16'h1500;
end
endtask

rtl/MEM12b4bA.v
// essentially, this memory block is a transparent register bank

module MEM12b4bA (
    input [15:0] addressA,
    input [15:0] addressB,
    input [15:0] dataInA,
    input [15:0] dataInB,
    input writeEnableA,
    input writeEnableB,
	input clk,
    input rstz,
    output [15:0] dataOutA,
    output [15:0] dataOutB,
    inout dvdd,
    inout dgnd
);

// Memory array declaration
reg [7:0] memory [0:65535];

wire [15:0] nextAddrA, nextAddrB;

integer i;

assign nextAddrA = addressA + 1;
assign nextAddrB = addressB + 1;

always @ (negedge rstz) begin
	for (i = 0; i < 65536; i = i + 1) begin
		if (rstz == 1'b0) begin
			memory[i] = 8'b0;
		end
	end
end

// Memory Write Operations
always @(negedge clk)
begin
	if (rstz == 1'b1)begin
		if (writeEnableA == 1'b1) begin
			memory[addressA] <= dataInA[15:8];
			memory[nextAddrA] <= dataInA[7:0];
		end
		if (writeEnableB == 1'b1) begin
			memory[addressB] <= dataInB[15:8];
			memory[nextAddrB] <= dataInB[7:0];
		end
	end
end

// Memory Read Operations
assign dataOutA = {memory[addressA], memory[nextAddrA]};
assign dataOutB = {memory[addressB], memory[nextAddrB]};

endmodule

rtl/BC16bA.v
module BC16bA (
	input jSel,
	input cbz,
	output pcsel,
	inout dvdd,
	inout dgnd
);

assign pcsel = cbz | jSel;

endmodule

rtl/ALU16bA.v
module ALU16bA (
	input [15:0] opA, // Operand A (RA)
	input [15:0] opB, // Operand B (RB or C)
	input [15:0] opD, // Operand D (RD - read only)
	input [1:0] selType, // Type Select: Arithmetic, Logic, LD/ST, Conditional
	input [1:0] selOp, // Operation Select (Arithm: add, mul, rsa; Logic: and, or, not, xor; ...)
	output [15:0] res, // ALU result
	output cbz, // conditional branch zero flag
	inout dvdd,
	inout dgnd
);

wire [15:0] radd;
wire [15:0] rmul;
wire [15:0] rsra;
wire [15:0] ratm;

wire [15:0] rrand;
wire [15:0] ror;
wire [15:0] rnot;
wire [15:0] rxor;
wire [15:0] rlog;

wire [15:0] radr;
wire [15:0] rset;
wire [15:0] rmem;

wire [15:0] rlt;
wire [15:0] rbj; // RA + C for branches and jumps
wire [15:0] rcnd;

// Arithmetic Operations
assign radd = opA + opB;
assign rmul = opA * opB;
assign rsra = opA >> opB;

assign ratm = selOp[1] ? (selOp[0] ? rsra : rmul) : radd;

// Logic Operations
assign rrand = opA & opB;
assign ror = opA | opB;
assign rnot = ~opA;
assign rxor = opA ^ opB;

assign rlog = selOp[1] ? (selOp[0] ? rxor : rnot) : (selOp[0] ? ror : rrand);

// LD/ST Operations
assign radr = opA + opB;
assign rset = opB;

assign rmem = selOp[1] ? rset : radr; // if 1X => rset, else its LD/ST

// Conditionals
assign rlt = opA < opB ? 16'h0001 : 16'b0;
assign rbj = opA + opB;

assign rcnd = selOp[1] ? rbj : rlt;

// ALU Output
assign res = selType[1] ? ( selType[0] ? rcnd : rmem ) : (selType[0] ? rlog : ratm);
assign cbz = opD == 16'b0; // if opD == 0 => cbz = 1 else cbz = 0

endmodule

rtl/RF16bA.v
module RF16bA (
	input [1:0] rd,
	input [1:0] ra,
	input [1:0] rb,
	input [15:0] data,
        input clk,
	input rstz,
	input en,
	output [15:0] opA,
	output [15:0] opB,
	output [15:0] opD,
	inout dvdd,
	inout dgnd
);

parameter NREGISTERS = 4;
parameter WIDTH = 16;

reg [(WIDTH-1):0] r[0:(NREGISTERS-1)];

integer i;

// Define Registers R0 - R3
always @(posedge clk)
begin
	for (i = 0; i < NREGISTERS; i = i +1) begin
		if (!rstz) 
			r[i] <= 0;
		else if ((rd == i) & en)
			r[i] <= data;
		else
			r[i] = r[i];
	end
end

assign opA = ra == 2'b0 ? r[0] : (ra == 2'b01 ? r[1] : (ra == 2'b10 ? r[2] : r[3]));
assign opB = rb == 2'b0 ? r[0] : (rb == 2'b01 ? r[1] : (rb == 2'b10 ? r[2] : r[3]));
assign opD = rd == 2'b0 ? r[0] : (rd == 2'b01 ? r[1] : (rd == 2'b10 ? r[2] : r[3]));

endmodule

rtl/ID16bA.v
module ID16bA (
	input [15:0] instr, // 16 bit instruction to be decoded
        input clk, // system clock
	output [1:0] rd, // Destination Register D ID
	output [1:0] ra, // Operand Register A ID
	output [1:0] rb, // Operand Register B ID
	output [7:0] c, // Immediate / Constant
	output [1:0] selType, // muxsel for operation type (arithm, logic, mem, conditional / flow control)
	output [1:0] selOp, // muxsel for operation of a given type (ex: arithm -> adc, add, mul, sra)
	output selB, // muxsel for second operand (Register B or Constant C)
	output jsel, // jump select
	output cbzsel, // cbz select
	output msel, // mem op select (high if instruction is a LD)
	output memwen, // memory write enable (high if instruction is a store)
	output rfen, // register file write enable (high if instruction writes to a register)
	inout dvdd, // module digital supply
	inout dgnd // module digital ground
);

// instr = [opcode(3:0), rd(1:0), ra(1:0), rb(1:0) / c(7:0)]

wire [3:0] opcode;

assign opcode = instr[15:12];
assign rd = instr[11:10];
assign ra = instr[9:8];
assign rb = instr[1:0];
assign c = instr[7:0];
// selB = 1 if instruction is ADC(0), LD(8), ST(9), SET(A), LTC(D), CBZ(E) or
// JMP(F)
assign selB = opcode == 4'h0 | opcode[3:1] == 3'b100 | opcode == 4'ha | opcode == 4'hd | opcode[3:1] == 3'b111;

assign selType = opcode[3:2];
assign selOp = opcode[1:0];

assign memwen = opcode == 4'h9; // instr is ST
assign rfen = (opcode != 4'h9 & opcode != 4'he & opcode != 4'hf); // instr is not ST neither CBZ nor JMP
assign jsel = opcode == 4'hf; // instr is JMP
assign msel = opcode == 4'h8; // instr is LD
assign cbzsel = opcode == 4'he; // instr is CBZ

endmodule

rtl/MAS16bA.v
module MAS16bA (
	input [15:0] pg_instr, // program instruction => stored in memory in programming mode
	input pg, // programming mode (for writing the program to memory)
        input clk,
	input rstz,
	inout dvdd,
	inout dgnd
);

// Base Instruction Mem Address
parameter instrAddr = 16'h8000;

wire [15:0] instr;
wire [15:0] opa;
wire [15:0] opb;
wire [15:0] opc;
wire [15:0] opd;
wire [15:0] opb_alu;
wire [15:0] alu_res;
wire [15:0] mem_out;
wire [7:0] c;
wire [15:0] wbdata;
wire [1:0] ra, rb, rd, type, op;
wire selB;
wire jsel;
wire msel;
wire mwen;
wire wdataen;
wire rfen;
wire cbzsel;
wire cbz_flag;
wire cbz;
wire nextpc_flag;

wire rstzmem; // resets memory; cannot be just the reset signal, otherwise it deprograms the mem

wire [15:0] nextpc;
reg [15:0] pc;

assign opc = {{8{c[7]}}, c};

ID16bA id(
	.instr(instr),
	.clk(clk),
	.rd(rd),
	.ra(ra),
	.rb(rb),
	.c(c),
	.selType(type),
	.selOp(op),
	.selB(selB),
	.jsel(jsel),
	.msel(msel),
	.cbzsel(cbzsel),
	.memwen(mwen),
	.rfen(rfen),
	.dvdd(dvdd),
	.dgnd(dgnd)
);

RF16bA rf(
	.rd(rd),
	.ra(ra),
	.rb(rb),
	.data(wbdata), // write-back data
	.clk(clk),
	.rstz(rstz),
	.en(rfen),
	.opA(opa),
	.opB(opb),
	.opD(opd),
	.dvdd(dvdd),
	.dgnd(dgnd)	
);

assign opb_alu = selB ? opc : opb; // ALUs operand B will be C if ADC, LD, ST, ..., otherwise RB

ALU16bA alu(
	.opA(opa),
	.opB(opb_alu),
	.opD(opd),
	.selType(type),
	.selOp(op),
	.res(alu_res),
	.cbz(cbz_flag),
	.dvdd(dvdd),
	.dgnd(dgnd)
);

assign cbz = cbz_flag & cbzsel;

BC16bA bc(
	.jSel(jsel),
	.cbz(cbz),
	.pcsel(nextpc_flag),
	.dvdd(dvdd),
	.dgnd(dgnd)
);

assign rstzmem = !pg | rstz;
assign wdataen = !pg & mwen;

MEM12b4bA mem(
	.addressA(pc), // port A is for instructions => address A = PC
	.addressB(alu_res), // on memory operations, the ALU result is the memory address
	.dataInA(pg_instr),
	.dataInB(opd),
	.writeEnableA(pg),
	.writeEnableB(wdataen),
	.clk(clk),
	.rstz(rstzmem),
	.dataOutA(instr),
	.dataOutB(mem_out),
	.dvdd(dvdd),
	.dgnd(dgnd)
);

// Write-Back
assign wbdata = msel ? mem_out : alu_res;


assign nextpc = nextpc_flag ? pc + alu_res : pc + 2; // add 2B, since each instr. is 2B (except if CBZ/JMP)

// Program Count
always @(posedge clk) begin
	if (rstz == 0) begin
		pc <= instrAddr;
	end
	else if (pg == 0)
		pc <= nextpc;
	else
		pc <= pc + 2; // fully sequential on programming mode
end

endmodule

testbench/MAS16bA_tb.v
`timescale 1ns / 1ps

module MAS16bA_tb;

reg [15:0] instr;
reg clk, rstz, pg;
wire dvdd, dgnd;

MAS16bA uut (
	.pg_instr(instr),
	.pg(pg),
	.clk(clk),
	.rstz(rstz),
	.dvdd(dvdd),
	.dgnd(dgnd)
);

`include "program.v"

initial
begin
$dumpfile("dump.vcd");
$dumpvars(0, MAS16bA_tb);

// Shows the memory
/*for (integer j = 0; j < 65536; j = j+1) begin
		$dumpvars(0, uut.mem.memory[j]);
	end*/

clk = 0;
rstz = 1;
pg = 1;
instr = 16'h0000;
#10 rstz = 0;
#10 rstz = 1; pg = 0;
#10 rstz = 0; pg = 1;
#10 rstz = 1;

program();

/*instr = 16'h0001;
#10 instr = 16'h0502;
#10 instr = 16'h0a03;
#10 instr = 16'h0f04;
#10 instr = 16'h2e03;
#10 instr = 16'ha000;
#10 instr = 16'hf0fe;*/

#10 pg = 0; rstz = 0;
#10 rstz = 1;
for (integer i = 0; i < `NUM_INSTRUCTIONS; i = i + 1) begin
	#10 $display("instr: %h; R0 = %1d, R1 = %1d, R2 = %1d, R3 = %1d",uut.instr, uut.rf.r[0], uut.rf.r[1], uut.rf.r[2], uut.rf.r[3]);
end

$finish;
end

always #5 clk = ~clk;
endmodule

testbench/dump.vcd
$date
	Sun May 19 15:09:24 2024
$end
$version
	Icarus Verilog
$end
$timescale
	1ps
$end
$scope module MAS16bA_tb $end
$var wire 1 ! dgnd $end
$var wire 1 " dvdd $end
$var reg 1 # clk $end
$var reg 16 $ instr [15:0] $end
$var reg 1 % pg $end
$var reg 1 & rstz $end
$scope module uut $end
$var wire 1 ' cbz $end
$var wire 1 # clk $end
$var wire 1 ! dgnd $end
$var wire 1 " dvdd $end
$var wire 1 % pg $end
$var wire 16 ( pg_instr [15:0] $end
$var wire 1 & rstz $end
$var wire 1 ) rstzmem $end
$var wire 1 * wdataen $end
$var wire 16 + wbdata [15:0] $end
$var wire 2 , type [1:0] $end
$var wire 1 - selB $end
$var wire 1 . rfen $end
$var wire 2 / rd [1:0] $end
$var wire 2 0 rb [1:0] $end
$var wire 2 1 ra [1:0] $end
$var wire 16 2 opd [15:0] $end
$var wire 16 3 opc [15:0] $end
$var wire 16 4 opb_alu [15:0] $end
$var wire 16 5 opb [15:0] $end
$var wire 16 6 opa [15:0] $end
$var wire 2 7 op [1:0] $end
$var wire 1 8 nextpc_flag $end
$var wire 16 9 nextpc [15:0] $end
$var wire 1 : mwen $end
$var wire 1 ; msel $end
$var wire 16 < mem_out [15:0] $end
$var wire 1 = jsel $end
$var wire 16 > instr [15:0] $end
$var wire 1 ? cbzsel $end
$var wire 1 @ cbz_flag $end
$var wire 8 A c [7:0] $end
$var wire 16 B alu_res [15:0] $end
$var parameter 16 C instrAddr $end
$var reg 16 D pc [15:0] $end
$scope module alu $end
$var wire 1 ! dgnd $end
$var wire 1 " dvdd $end
$var wire 16 E opB [15:0] $end
$var wire 16 F rnot [15:0] $end
$var wire 16 G ror [15:0] $end
$var wire 16 H rrand [15:0] $end
$var wire 16 I rset [15:0] $end
$var wire 16 J rxor [15:0] $end
$var wire 2 K selType [1:0] $end
$var wire 2 L selOp [1:0] $end
$var wire 16 M rsra [15:0] $end
$var wire 16 N rmul [15:0] $end
$var wire 16 O rmem [15:0] $end
$var wire 16 P rlt [15:0] $end
$var wire 16 Q rlog [15:0] $end
$var wire 16 R res [15:0] $end
$var wire 16 S rcnd [15:0] $end
$var wire 16 T rbj [15:0] $end
$var wire 16 U ratm [15:0] $end
$var wire 16 V radr [15:0] $end
$var wire 16 W radd [15:0] $end
$var wire 16 X opD [15:0] $end
$var wire 16 Y opA [15:0] $end
$var wire 1 @ cbz $end
$upscope $end
$scope module bc $end
$var wire 1 ' cbz $end
$var wire 1 ! dgnd $end
$var wire 1 " dvdd $end
$var wire 1 8 pcsel $end
$var wire 1 = jSel $end
$upscope $end
$scope module id $end
$var wire 1 # clk $end
$var wire 1 ! dgnd $end
$var wire 1 " dvdd $end
$var wire 1 . rfen $end
$var wire 1 - selB $end
$var wire 2 Z selType [1:0] $end
$var wire 2 [ selOp [1:0] $end
$var wire 2 \ rd [1:0] $end
$var wire 2 ] rb [1:0] $end
$var wire 2 ^ ra [1:0] $end
$var wire 4 _ opcode [3:0] $end
$var wire 1 ; msel $end
$var wire 1 : memwen $end
$var wire 1 = jsel $end
$var wire 16 ` instr [15:0] $end
$var wire 1 ? cbzsel $end
$var wire 8 a c [7:0] $end
$upscope $end
$scope module mem $end
$var wire 16 b addressA [15:0] $end
$var wire 16 c addressB [15:0] $end
$var wire 1 # clk $end
$var wire 16 d dataInA [15:0] $end
$var wire 1 ! dgnd $end
$var wire 1 " dvdd $end
$var wire 1 ) rstz $end
$var wire 1 % writeEnableA $end
$var wire 1 * writeEnableB $end
$var wire 16 e nextAddrB [15:0] $end
$var wire 16 f nextAddrA [15:0] $end
$var wire 16 g dataOutB [15:0] $end
$var wire 16 h dataOutA [15:0] $end
$var wire 16 i dataInB [15:0] $end
$var integer 32 j i [31:0] $end
$upscope $end
$scope module rf $end
$var wire 1 # clk $end
$var wire 16 k data [15:0] $end
$var wire 1 ! dgnd $end
$var wire 1 " dvdd $end
$var wire 1 . en $end
$var wire 2 l ra [1:0] $end
$var wire 2 m rb [1:0] $end
$var wire 2 n rd [1:0] $end
$var wire 1 & rstz $end
$var wire 16 o opD [15:0] $end
$var wire 16 p opB [15:0] $end
$var wire 16 q opA [15:0] $end
$var parameter 32 r NREGISTERS $end
$var parameter 32 s WIDTH $end
$var integer 32 t i [31:0] $end
$upscope $end
$upscope $end
$scope begin $ivl_for_loop0 $end
$var integer 32 u i [31:0] $end
$upscope $end
$scope task program $end
$upscope $end
$upscope $end
$enddefinitions $end
$comment Show the parameter values. $end
$dumpall
b10000 s
b100 r
b1000000000000000 C
$end
#0
$dumpvars
bx u
bx t
bx q
bx p
bx o
bx n
bx m
bx l
bx k
bx j
bx i
bx h
bx g
bx f
bx e
b0 d
bx c
bx b
bx a
bx `
bx _
bx ^
bx ]
bx \
bx [
bx Z
bx Y
bx X
bx W
bx V
bx U
bx T
bx S
bx R
bx Q
b0x P
bx O
bx N
bx M
bx L
bx K
bx J
bx I
bx H
bx G
bx F
bx E
bx D
bx B
bx A
x@
x?
bx >
x=
bx <
x;
x:
bx 9
x8
bx 7
bx 6
bx 5
bx 4
bx 3
bx 2
bx 1
bx 0
bx /
x.
x-
bx ,
bx +
0*
1)
b0 (
x'
1&
1%
b0 $
0#
z"
z!
$end
#5000
b100 t
1#
#10000
b10000000000000000 j
0)
0#
0&
#15000
b0 +
b0 k
1-
b1 e
b0 <
b0 g
b0 B
b0 R
b0 c
b0 Q
b0 U
b0 O
b0 P
b0 S
b0 J
b1111111111111111 F
b0 G
b0 H
1.
b1000000000000010 9
b0 I
b0 W
b0 N
b0 M
b0 V
b0 T
b0 4
b0 E
b0 5
b0 p
b0 6
b0 Y
b0 q
1@
b0 2
b0 X
b0 i
b0 o
b0 ,
b0 K
b0 Z
b0 7
b0 L
b0 [
08
0'
b0 3
b0 A
b0 a
b0 0
b0 ]
b0 m
b0 1
b0 ^
b0 l
b0 /
b0 \
b0 n
0:
0=
0;
0?
b0 _
b1000000000000001 f
b0 >
b0 `
b0 h
b1000000000000000 D
b1000000000000000 b
b100 t
1#
#20000
1)
0#
0%
1&
#25000
b1000000000000100 9
b1000000000000011 f
b1000000000000010 D
b1000000000000010 b
b100 t
1#
#30000
b10000000000000000 j
0)
0#
1%
0&
#35000
b1000000000000010 9
b1000000000000001 f
b1000000000000000 D
b1000000000000000 b
b100 t
1#
#40000
1)
0#
1&
#45000
b1000000000000100 9
b1000000000000011 f
b1000000000000010 D
b1000000000000010 b
b100 t
1#
#50000
b1100100 +
b1100100 k
b1100101 e
b1100100 B
b1100100 R
b1100100 c
b1100100 S
b1111111111111111 Q
b1100100 G
b1100100 J
b1100100 O
b1 P
b1100100 I
b1100100 W
b1100100 V
b1100100 T
b1100100 4
b1100100 E
b10 ,
b10 K
b10 Z
b10 7
b10 L
b10 [
b1100100 3
b1100100 A
b1100100 a
b1010 _
b1010000001100100 >
b1010000001100100 `
b1010000001100100 h
0#
b1010000001100100 $
b1010000001100100 (
b1010000001100100 d
#55000
b1100100 O
b1100100 +
b1100100 k
1-
b1100101 e
b1100100 B
b1100100 R
b1100100 c
b0 Q
b1100100 U
b0 I
b1100100 M
b0 4
b0 E
b0 ,
b0 K
b0 Z
b0 7
b0 L
b0 [
b0 S
b0 P
b1100100 J
b1111111110011011 F
b0 H
b1000000000000110 9
b0 3
b0 A
b0 a
b0 _
b1100100 T
b1100100 V
b0 N
b1100100 W
b1100100 6
b1100100 Y
b1100100 q
b1100100 5
b1100100 p
0@
b1100100 2
b1100100 X
b1100100 i
b1100100 o
b1000000000000101 f
b0 >
b0 `
b0 h
b1000000000000100 D
b1000000000000100 b
b100 t
1#
#60000
b101000 +
b101000 k
b101001 e
b101000 B
b101000 R
b101000 c
b10001100 S
b1111111110011011 Q
b100000 H
b1101100 G
b1001100 J
b111110100000 U
b101000 O
b101000 I
b10001100 W
b111110100000 N
b0 M
b10001100 V
b10001100 T
b101000 4
b101000 E
1@
b0 2
b0 X
b0 i
b0 o
b10 ,
b10 K
b10 Z
b10 7
b10 L
b10 [
b101000 3
b101000 A
b101000 a
b1 /
b1 \
b1 n
b1010 _
b1010010000101000 >
b1010010000101000 `
b1010010000101000 h
0#
b1010010000101000 $
b1010010000101000 (
b1010010000101000 d
#65000
b1100100 +
b1100100 k
1-
b1100101 e
b1100100 B
b1100100 R
b1100100 c
b0 Q
b1100100 U
b0 H
b1100100 G
b1100100 J
b1100100 O
b0 S
b0 I
b1100100 W
b0 N
b1100100 M
b1100100 V
b1100100 T
b0 4
b0 E
0@
b1100100 2
b1100100 X
b1100100 i
b1100100 o
b0 ,
b0 K
b0 Z
b0 7
b0 L
b0 [
b1000000000001000 9
b0 3
b0 A
b0 a
b0 /
b0 \
b0 n
b0 _
b1000000000000111 f
b0 >
b0 `
b0 h
b1000000000000110 D
b1000000000000110 b
b100 t
1#
#70000
b1100100 Q
0.
b101000 2
b101000 X
b101000 i
b101000 o
b10 ,
b10 K
b10 Z
b1 7
b1 L
b1 [
b1 /
b1 \
b1 n
1:
b1001 _
b1001010000000000 >
b1001010000000000 `
b1001010000000000 h
0#
b1001010000000000 $
b1001010000000000 (
b1001010000000000 d
#75000
b0 Q
1.
b1100100 2
b1100100 X
b1100100 i
b1100100 o
b0 ,
b0 K
b0 Z
b0 7
b0 L
b0 [
b1000000000001010 9
b0 /
b0 \
b0 n
0:
b0 _
b1000000000001001 f
b0 >
b0 `
b0 h
b1000000000001000 D
b1000000000001000 b
b100 t
1#
#80000
b110010 +
b110010 k
b110011 e
b110010 B
b110010 R
b110010 c
b10010110 S
b1111111110011011 Q
b100000 H
b1110110 G
b1010110 J
b1001110001000 U
b110010 O
b110010 I
b10010110 W
b1001110001000 N
b0 M
b10010110 V
b10010110 T
b110010 4
b110010 E
b0 5
b0 p
b101000 2
b101000 X
b101000 i
b101000 o
b10 ,
b10 K
b10 Z
b10 7
b10 L
b10 [
b110010 3
b110010 A
b110010 a
b10 0
b10 ]
b10 m
b1 /
b1 \
b1 n
b1010 _
b1010010000110010 >
b1010010000110010 `
b1010010000110010 h
0#
b1010010000110010 $
b1010010000110010 (
b1010010000110010 d
#85000
b1100100 +
b1100100 k
1-
b1100101 e
b1100100 B
b1100100 R
b1100100 c
b0 Q
b1100100 U
b0 H
b1100100 G
b1100100 J
b1100100 O
b0 S
b0 I
b1100100 W
b0 N
b1100100 M
b1100100 V
b1100100 T
b0 4
b0 E
b1100100 5
b1100100 p
b1100100 2
b1100100 X
b1100100 i
b1100100 o
b0 ,
b0 K
b0 Z
b0 7
b0 L
b0 [
b1000000000001100 9
b0 3
b0 A
b0 a
b0 0
b0 ]
b0 m
b0 /
b0 \
b0 n
b0 _
b1000000000001011 f
b0 >
b0 `
b0 h
b1000000000001010 D
b1000000000001010 b
b100 t
1#
#90000
b1100110 +
b1100110 k
b1100111 e
b1100110 B
b1100110 R
b1100110 c
b1100110 Q
b1100110 G
b1100110 J
b1100110 U
b1100110 O
0.
b10 I
b1100110 W
b11001000 N
b11001 M
b1100110 V
b1100110 T
b10 4
b10 E
b0 5
b0 p
b110010 2
b110010 X
b110010 i
b110010 o
b10 ,
b10 K
b10 Z
b1 7
b1 L
b1 [
b10 3
b10 A
b10 a
b10 0
b10 ]
b10 m
b1 /
b1 \
b1 n
1:
b1001 _
b1001010000000010 >
b1001010000000010 `
b1001010000000010 h
0#
b1001010000000010 $
b1001010000000010 (
b1001010000000010 d
#95000
b1100100 +
b1100100 k
b1100101 e
b1100100 B
b1100100 R
b1100100 c
b0 Q
b1100100 G
b1100100 J
b1100100 U
b1100100 O
1.
b0 I
b1100100 W
b0 N
b1100100 M
b1100100 V
b1100100 T
b0 4
b0 E
b1100100 5
b1100100 p
b1100100 2
b1100100 X
b1100100 i
b1100100 o
b0 ,
b0 K
b0 Z
b0 7
b0 L
b0 [
b1000000000001110 9
b0 3
b0 A
b0 a
b0 0
b0 ]
b0 m
b0 /
b0 \
b0 n
0:
b0 _
b1000000000001101 f
b0 >
b0 `
b0 h
b1000000000001100 D
b1000000000001100 b
b100 t
1#
#100000
b11110 +
b11110 k
b11111 e
b11110 B
b11110 R
b11110 c
b10000010 S
b1111111110011011 Q
b100 H
b1111110 G
b1111010 J
b101110111000 U
b11110 O
b11110 I
b10000010 W
b101110111000 N
b0 M
b10000010 V
b10000010 T
b11110 4
b11110 E
b0 5
b0 p
b110010 2
b110010 X
b110010 i
b110010 o
b10 ,
b10 K
b10 Z
b10 7
b10 L
b10 [
b11110 3
b11110 A
b11110 a
b10 0
b10 ]
b10 m
b1 /
b1 \
b1 n
b1010 _
b1010010000011110 >
b1010010000011110 `
b1010010000011110 h
0#
b1010010000011110 $
b1010010000011110 (
b1010010000011110 d
#105000
b1100100 +
b1100100 k
1-
b1100101 e
b1100100 B
b1100100 R
b1100100 c
b0 Q
b1100100 U
b0 H
b1100100 G
b1100100 J
b1100100 O
b0 S
b0 I
b1100100 W
b0 N
b1100100 M
b1100100 V
b1100100 T
b0 4
b0 E
b1100100 5
b1100100 p
b1100100 2
b1100100 X
b1100100 i
b1100100 o
b0 ,
b0 K
b0 Z
b0 7
b0 L
b0 [
b1000000000010000 9
b0 3
b0 A
b0 a
b0 0
b0 ]
b0 m
b0 /
b0 \
b0 n
b0 _
b1000000000001111 f
b0 >
b0 `
b0 h
b1000000000001110 D
b1000000000001110 b
b100 t
1#
#110000
b1101000 +
b1101000 k
b1101001 e
b1101000 B
b1101000 R
b1101000 c
b1100100 Q
b100 H
b1100000 J
b1101000 U
b1101000 O
0.
b100 I
b1101000 W
b110010000 N
b110 M
b1101000 V
b1101000 T
b100 4
b100 E
b11110 2
b11110 X
b11110 i
b11110 o
b10 ,
b10 K
b10 Z
b1 7
b1 L
b1 [
b100 3
b100 A
b100 a
b1 /
b1 \
b1 n
1:
b1001 _
b1001010000000100 >
b1001010000000100 `
b1001010000000100 h
0#
b1001010000000100 $
b1001010000000100 (
b1001010000000100 d
#115000
b1100100 +
b1100100 k
b1100101 e
b1100100 B
b1100100 R
b1100100 c
b0 Q
b0 H
b1100100 J
b1100100 U
b1100100 O
1.
b0 I
b1100100 W
b0 N
b1100100 M
b1100100 V
b1100100 T
b0 4
b0 E
b1100100 2
b1100100 X
b1100100 i
b1100100 o
b0 ,
b0 K
b0 Z
b0 7
b0 L
b0 [
b1000000000010010 9
b0 3
b0 A
b0 a
b0 /
b0 \
b0 n
0:
b0 _
b1000000000010001 f
b0 >
b0 `
b0 h
b1000000000010000 D
b1000000000010000 b
b100 t
1#
#120000
b110010 +
b110010 k
b110011 e
b110010 B
b110010 R
b110010 c
b10010110 S
b1111111110011011 Q
b100000 H
b1110110 G
b1010110 J
b1001110001000 U
b110010 O
b110010 I
b10010110 W
b1001110001000 N
b0 M
b10010110 V
b10010110 T
b110010 4
b110010 E
b0 5
b0 p
b11110 2
b11110 X
b11110 i
b11110 o
b10 ,
b10 K
b10 Z
b10 7
b10 L
b10 [
b110010 3
b110010 A
b110010 a
b10 0
b10 ]
b10 m
b1 /
b1 \
b1 n
b1010 _
b1010010000110010 >
b1010010000110010 `
b1010010000110010 h
0#
b1010010000110010 $
b1010010000110010 (
b1010010000110010 d
#125000
b1100100 +
b1100100 k
1-
b1100101 e
b1100100 B
b1100100 R
b1100100 c
b0 Q
b1100100 U
b0 H
b1100100 G
b1100100 J
b1100100 O
b0 S
b0 I
b1100100 W
b0 N
b1100100 M
b1100100 V
b1100100 T
b0 4
b0 E
b1100100 5
b1100100 p
b1100100 2
b1100100 X
b1100100 i
b1100100 o
b0 ,
b0 K
b0 Z
b0 7
b0 L
b0 [
b1000000000010100 9
b0 3
b0 A
b0 a
b0 0
b0 ]
b0 m
b0 /
b0 \
b0 n
b0 _
b1000000000010011 f
b0 >
b0 `
b0 h
b1000000000010010 D
b1000000000010010 b
b100 t
1#
#130000
b1101010 +
b1101010 k
b1101011 e
b1101010 B
b1101010 R
b1101010 c
b1100110 Q
b100 H
b1100110 G
b1100010 J
b1101010 U
b1101010 O
0.
b110 I
b1101010 W
b1001011000 N
b1 M
b1101010 V
b1101010 T
b110 4
b110 E
b0 5
b0 p
b110010 2
b110010 X
b110010 i
b110010 o
b10 ,
b10 K
b10 Z
b1 7
b1 L
b1 [
b110 3
b110 A
b110 a
b10 0
b10 ]
b10 m
b1 /
b1 \
b1 n
1:
b1001 _
b1001010000000110 >
b1001010000000110 `
b1001010000000110 h
0#
b1001010000000110 $
b1001010000000110 (
b1001010000000110 d
#135000
b1100100 +
b1100100 k
b1100101 e
b1100100 B
b1100100 R
b1100100 c
b0 Q
b0 H
b1100100 G
b1100100 J
b1100100 U
b1100100 O
1.
b0 I
b1100100 W
b0 N
b1100100 M
b1100100 V
b1100100 T
b0 4
b0 E
b1100100 5
b1100100 p
b1100100 2
b1100100 X
b1100100 i
b1100100 o
b0 ,
b0 K
b0 Z
b0 7
b0 L
b0 [
b1000000000010110 9
b0 3
b0 A
b0 a
b0 0
b0 ]
b0 m
b0 /
b0 \
b0 n
0:
b0 _
b1000000000010101 f
b0 >
b0 `
b0 h
b1000000000010100 D
b1000000000010100 b
b100 t
1#
#140000
b11110 +
b11110 k
b11111 e
b11110 B
b11110 R
b11110 c
b10000010 S
b1111111110011011 Q
b100 H
b1111110 G
b1111010 J
b101110111000 U
b11110 O
b11110 I
b10000010 W
b101110111000 N
b0 M
b10000010 V
b10000010 T
b11110 4
b11110 E
b0 5
b0 p
b110010 2
b110010 X
b110010 i
b110010 o
b10 ,
b10 K
b10 Z
b10 7
b10 L
b10 [
b11110 3
b11110 A
b11110 a
b10 0
b10 ]
b10 m
b1 /
b1 \
b1 n
b1010 _
b1010010000011110 >
b1010010000011110 `
b1010010000011110 h
0#
b1010010000011110 $
b1010010000011110 (
b1010010000011110 d
#145000
b1100100 +
b1100100 k
1-
b1100101 e
b1100100 B
b1100100 R
b1100100 c
b0 Q
b1100100 U
b0 H
b1100100 G
b1100100 J
b1100100 O
b0 S
b0 I
b1100100 W
b0 N
b1100100 M
b1100100 V
b1100100 T
b0 4
b0 E
b1100100 5
b1100100 p
b1100100 2
b1100100 X
b1100100 i
b1100100 o
b0 ,
b0 K
b0 Z
b0 7
b0 L
b0 [
b1000000000011000 9
b0 3
b0 A
b0 a
b0 0
b0 ]
b0 m
b0 /
b0 \
b0 n
b0 _
b1000000000010111 f
b0 >
b0 `
b0 h
b1000000000010110 D
b1000000000010110 b
b100 t
1#
