testbench/program.v
`define NUM_INSTRUCTIONS 63

task program(); begin
	#10 instr = 16'hA001;
	#10 instr = 16'hA402;
	#10 instr = 16'hAC7F;
	#10 instr = 16'h2F03;
	#10 instr = 16'h2001;
	#10 instr = 16'hC803;
	#10 instr = 16'hDA01;
	#10 instr = 16'hE9F8;
	#10 instr = 16'h00FF;
end
endtask

rtl/MEM12b4bA.v
module MEM12b4bA (
    input [15:0] addressA,
    input [15:0] addressB,
    input [15:0] dataInA,
    input [15:0] dataInB,
    input writeEnableA,
    input writeEnableB,
    input rstz,
    output [15:0] dataOutA,
    output [15:0] dataOutB,
    inout dvdd,
    inout dgnd
);

// Memory array declaration
reg [7:0] memory [0:16383][0:3]; // 2^14 rows, each with 2^2 columns

wire [15:0] nextAddrA, nextAddrB;

assign nextAddrA = addressA + 1;
assign nextAddrB = addressB + 1;

always @ (negedge rstz) begin
	for (integer i = 0; i < 16384; i = i + 1) begin
		if (rstz == 1'b0) begin
			memory[i][0] <= 8'b0;
			memory[i][1] <= 8'b0;
			memory[i][2] <= 8'b0;
			memory[i][3] <= 8'b0;
		end
	end
end

// Memory Write Operations
always @ (posedge writeEnableA or posedge writeEnableB or addressA or addressB)
begin
	if (rstz == 1'b1) begin
		if (writeEnableA) begin
        		memory[addressA[15:2]][addressA[1:0]] <= dataInA[15:8];
			memory[nextAddrA[15:2]][nextAddrA[1:0]] <= dataInA[7:0];
		end
		if (writeEnableB) begin
			memory[addressB[15:2]][addressB[1:0]] <= dataInB[15:8];
			memory[nextAddrB[15:2]][nextAddrB[1:0]] <= dataInB[7:0];
		end
	end
end 

// Memory Read Operations
assign dataOutA = {memory[addressA[15:2]][addressA[1:0]], memory[nextAddrA[15:2]][nextAddrA[1:0]]};
assign dataOutB = {memory[addressB[15:2]][addressB[1:0]], memory[nextAddrB[15:2]][nextAddrB[1:0]]};

endmodule

rtl/BC16bA.v
module BC16bA (
	input jSel,
	input cbz,
	output pcsel,
	inout dvdd,
	inout dgnd
);

assign pcsel = cbz | jSel;

endmodule

rtl/ALU16bA.v
module ALU16bA (
	input [15:0] opA, // Operand A (RA)
	input [15:0] opB, // Operand B (RB or C)
	input [15:0] opD, // Operand D (RD - read only)
	input [1:0] selType, // Type Select: Arithmetic, Logic, LD/ST, Conditional
	input [1:0] selOp, // Operation Select (Arithm: add, mul, rsa; Logic: and, or, not, xor; ...)
	output [15:0] res, // ALU result
	output cbz, // conditional branch zero flag
	inout dvdd,
	inout dgnd
);

wire [15:0] radd;
wire [15:0] rmul;
wire [15:0] rsra;
wire [15:0] ratm;

wire [15:0] rand;
wire [15:0] ror;
wire [15:0] rnot;
wire [15:0] rxor;
wire [15:0] rlog;

wire [15:0] radr;
wire [15:0] rset;
wire [15:0] rmem;

wire [15:0] rlt;
wire [15:0] rbj; // RA + C for branches and jumps
wire [15:0] rcnd;

// Arithmetic Operations
assign radd = opA + opB;
assign rmul = opA * opB;
assign rsra = opA >> opB;

assign ratm = selOp[1] ? (selOp[0] ? rsra : rmul) : radd;

// Logic Operations
assign rand = opA & opB;
assign ror = opA | opB;
assign rnot = ~opA;
assign rxor = opA ^ opB;

assign rlog = selOp[1] ? (selOp[0] ? rxor : rnot) : (selOp[0] ? ror : rand);

// LD/ST Operations
assign radr = opA + opB;
assign rset = opB;

assign rmem = selOp[1] ? rset : radr; // if 1X => rset, else its LD/ST

// Conditionals
assign rlt = opA < opB ? 16'h0001 : 16'b0;
assign rbj = opA + opB;

assign rcnd = selOp[1] ? rbj : rlt;

// ALU Output
assign res = selType[1] ? ( selType[0] ? rcnd : rmem ) : (selType[0] ? rlog : ratm);
assign cbz = opD == 16'b0; // if opD == 0 => cbz = 1 else cbz = 0

endmodule

rtl/RF16bA.v
module RF16bA (
	input [1:0] rd,
	input [1:0] ra,
	input [1:0] rb,
	input [15:0] data,
        input clk,
	input rstz,
	input en,
	output [15:0] opA,
	output [15:0] opB,
	output [15:0] opD,
	inout dvdd,
	inout dgnd
);

parameter NREGISTERS = 4;
parameter WIDTH = 16;

reg [(WIDTH-1):0] r[0:(NREGISTERS-1)];

integer i;

// Define Registers R0 - R3
always @(posedge clk)
begin
	for (i = 0; i < NREGISTERS; i = i +1) begin
		if (!rstz) 
			r[i] <= 0;
		else if ((rd == i) & en)
			r[i] <= data;
		else
			r[i] = r[i];
	end
end

assign opA = ra == 2'b0 ? r[0] : (ra == 2'b01 ? r[1] : (ra == 2'b10 ? r[2] : r[3]));
assign opB = rb == 2'b0 ? r[0] : (rb == 2'b01 ? r[1] : (rb == 2'b10 ? r[2] : r[3]));
assign opD = rd == 2'b0 ? r[0] : (rd == 2'b01 ? r[1] : (rd == 2'b10 ? r[2] : r[3]));

endmodule

rtl/ID16bA.v
module ID16bA (
	input [15:0] instr, // 16 bit instruction to be decoded
        input clk, // system clock
	output [1:0] rd, // Destination Register D ID
	output [1:0] ra, // Operand Register A ID
	output [1:0] rb, // Operand Register B ID
	output [7:0] c, // Immediate / Constant
	output [1:0] selType, // muxsel for operation type (arithm, logic, mem, conditional / flow control)
	output [1:0] selOp, // muxsel for operation of a given type (ex: arithm -> adc, add, mul, sra)
	output selB, // muxsel for second operand (Register B or Constant C)
	output jsel, // jump select
	output cbzsel, // cbz select
	output msel, // mem op select (high if instruction is a LD)
	output memwen, // memory write enable (high if instruction is a store)
	output rfen, // register file write enable (high if instruction writes to a register)
	inout dvdd, // module digital supply
	inout dgnd // module digital ground
);

// instr = [opcode(3:0), rd(1:0), ra(1:0), rb(1:0) / c(7:0)]

wire [3:0] opcode;

assign opcode = instr[15:12];
assign rd = instr[11:10];
assign ra = instr[9:8];
assign rb = instr[1:0];
assign c = instr[7:0];
// selB = 1 if instruction is ADC(0), LD(8), ST(9), SET(A), LTC(D), CBZ(E) or
// JMP(F)
assign selB = opcode == 4'h0 | opcode[3:1] == 3'b100 | opcode == 4'ha | opcode == 4'hd | opcode[3:1] == 3'b111;

assign selType = opcode[3:2];
assign selOp = opcode[1:0];

assign memwen = opcode == 4'h9; // instr is ST
assign rfen = (opcode != 4'h9 & opcode != 4'he & opcode != 4'hf); // instr is not ST neither CBZ nor JMP
assign jsel = opcode == 4'hf; // instr is JMP
assign msel = opcode == 4'h8; // instr is LD
assign cbzsel = opcode == 4'he; // instr is CBZ

endmodule

rtl/MAS16bA.v
module MAS16bA (
	input [15:0] pg_instr, // program instruction => stored in memory in programming mode
	input pg, // programming mode (for writing the program to memory)
        input clk,
	input rstz,
	inout dvdd,
	inout dgnd
);

// Base Instruction Mem Address
parameter instrAddr = 16'h8000;

wire [15:0] instr;
wire [15:0] opa;
wire [15:0] opb;
wire [15:0] opc;
wire [15:0] opd;
wire [15:0] opb_alu;
wire [15:0] alu_res;
wire [15:0] mem_out;
wire [7:0] c;
wire [15:0] wbdata;
wire [1:0] ra, rb, rd, type, op;
wire selB;
wire jsel;
wire msel;
wire mwen;
wire rfen;
wire cbzsel;
wire cbz_flag;
wire cbz;
wire nextpc_flag;

wire rstzmem; // resets memory; cannot be just the reset signal, otherwise it deprograms the mem

wire [15:0] nextpc;
reg [15:0] pc;

assign opc = {{8{c[7]}}, c};

ID16bA id(
	.instr(instr),
	.clk(clk),
	.rd(rd),
	.ra(ra),
	.rb(rb),
	.c(c),
	.selType(type),
	.selOp(op),
	.selB(selB),
	.jsel(jsel),
	.msel(msel),
	.cbzsel(cbzsel),
	.memwen(mwen),
	.rfen(rfen),
	.dvdd(dvdd),
	.dgnd(dgnd)
);

RF16bA rf(
	.rd(rd),
	.ra(ra),
	.rb(rb),
	.data(wbdata), // write-back data
	.clk(clk),
	.rstz(rstz),
	.en(rfen),
	.opA(opa),
	.opB(opb),
	.opD(opd),
	.dvdd(dvdd),
	.dgnd(dgnd)	
);

assign opb_alu = selB ? opc : opb; // ALUs operand B will be C if ADC, LD, ST, ..., otherwise RB

ALU16bA alu(
	.opA(opa),
	.opB(opb_alu),
	.opD(opd),
	.selType(type),
	.selOp(op),
	.res(alu_res),
	.cbz(cbz_flag),
	.dvdd(dvdd),
	.dgnd(dgnd)
);

assign cbz = cbz_flag & cbzsel;

BC16bA bc(
	.jSel(jsel),
	.cbz(cbz),
	.pcsel(nextpc_flag),
	.dvdd(dvdd),
	.dgnd(dgnd)
);

assign rstzmem = !pg | rstz;

MEM12b4bA mem(
	.addressA(pc), // port A is for instructions => address A = PC
	.addressB(alu_res), // on memory operations, the ALU result is the memory address
	.dataInA(pg_instr),
	.dataInB(opd),
	.writeEnableA(pg),
	.writeEnableB(mwen),
	.rstz(rstzmem),
	.dataOutA(instr),
	.dataOutB(mem_out),
	.dvdd(dvdd),
	.dgnd(dgnd)
);

// Write-Back
assign wbdata = msel ? mem_out : alu_res;


assign nextpc = nextpc_flag ? pc + alu_res : pc + 2; // add 2B, since each instr. is 2B (except if CBZ/JMP)

// Program Count
always @(posedge clk) begin
	if (rstz == 0) begin
		pc <= instrAddr;
	end
	else if (pg == 0)
		pc <= nextpc;
	else
		pc <= pc + 2; // fully sequential on programming mode
end

endmodule

testbench/MAS16bA_tb.v
`timescale 1ns / 1ps

module MAS16bA_tb;

reg [15:0] instr;
reg clk, rstz, pg;
wire dvdd, dgnd;

MAS16bA uut (
	.pg_instr(instr),
	.pg(pg),
	.clk(clk),
	.rstz(rstz),
	.dvdd(dvdd),
	.dgnd(dgnd)
);

`include "program.v"

initial
begin
$dumpfile("dump.vcd");
$dumpvars(0, MAS16bA_tb);

// Shows the memory
/*for (integer j = 0; j < 65536; j = j+1) begin
		$dumpvars(0, uut.mem.memory[j]);
	end*/

clk = 0;
rstz = 1;
pg = 1;
instr = 16'h0000;
#10 rstz = 0;
#10 rstz = 1; pg = 0;
#10 rstz = 0; pg = 1;
#10 rstz = 1;

program();

/*instr = 16'h0001;
#10 instr = 16'h0502;
#10 instr = 16'h0a03;
#10 instr = 16'h0f04;
#10 instr = 16'h2e03;
#10 instr = 16'ha000;
#10 instr = 16'hf0fe;*/

#10 instr = 16'ha000;
#10 instr = 16'hf000; // end program

#10 pg = 0; rstz = 0;
#10 rstz = 1;
for (integer i = 0; i < `NUM_INSTRUCTIONS; i = i + 1) begin
	#10 $display("instr: %h; R0 = %1d, R1 = %1d, R2 = %1d, R3 = %1d",uut.instr, uut.rf.r[0], uut.rf.r[1], uut.rf.r[2], uut.rf.r[3]);
end

$finish;
end

always #5 clk = ~clk;
endmodule

testbench/dump.vcd
$date
	Sat May 18 12:08:54 2024
$end
$version
	Icarus Verilog
$end
$timescale
	1ps
$end
$scope module MAS16bA_tb $end
$var wire 1 ! dgnd $end
$var wire 1 " dvdd $end
$var reg 1 # clk $end
$var reg 16 $ instr [15:0] $end
$var reg 1 % pg $end
$var reg 1 & rstz $end
$scope module uut $end
$var wire 1 ' cbz $end
$var wire 1 # clk $end
$var wire 1 ! dgnd $end
$var wire 1 " dvdd $end
$var wire 1 % pg $end
$var wire 16 ( pg_instr [15:0] $end
$var wire 1 & rstz $end
$var wire 1 ) rstzmem $end
$var wire 16 * wbdata [15:0] $end
$var wire 2 + type [1:0] $end
$var wire 1 , selB $end
$var wire 1 - rfen $end
$var wire 2 . rd [1:0] $end
$var wire 2 / rb [1:0] $end
$var wire 2 0 ra [1:0] $end
$var wire 16 1 opd [15:0] $end
$var wire 16 2 opc [15:0] $end
$var wire 16 3 opb_alu [15:0] $end
$var wire 16 4 opb [15:0] $end
$var wire 16 5 opa [15:0] $end
$var wire 2 6 op [1:0] $end
$var wire 1 7 nextpc_flag $end
$var wire 16 8 nextpc [15:0] $end
$var wire 1 9 mwen $end
$var wire 1 : msel $end
$var wire 16 ; mem_out [15:0] $end
$var wire 1 < jsel $end
$var wire 16 = instr [15:0] $end
$var wire 1 > cbzsel $end
$var wire 1 ? cbz_flag $end
$var wire 8 @ c [7:0] $end
$var wire 16 A alu_res [15:0] $end
$var parameter 16 B instrAddr $end
$var reg 16 C pc [15:0] $end
$scope module alu $end
$var wire 1 ! dgnd $end
$var wire 1 " dvdd $end
$var wire 16 D opB [15:0] $end
$var wire 16 E rand [15:0] $end
$var wire 16 F rnot [15:0] $end
$var wire 16 G ror [15:0] $end
$var wire 16 H rset [15:0] $end
$var wire 16 I rxor [15:0] $end
$var wire 2 J selType [1:0] $end
$var wire 2 K selOp [1:0] $end
$var wire 16 L rsra [15:0] $end
$var wire 16 M rmul [15:0] $end
$var wire 16 N rmem [15:0] $end
$var wire 16 O rlt [15:0] $end
$var wire 16 P rlog [15:0] $end
$var wire 16 Q res [15:0] $end
$var wire 16 R rcnd [15:0] $end
$var wire 16 S rbj [15:0] $end
$var wire 16 T ratm [15:0] $end
$var wire 16 U radr [15:0] $end
$var wire 16 V radd [15:0] $end
$var wire 16 W opD [15:0] $end
$var wire 16 X opA [15:0] $end
$var wire 1 ? cbz $end
$upscope $end
$scope module bc $end
$var wire 1 ' cbz $end
$var wire 1 ! dgnd $end
$var wire 1 " dvdd $end
$var wire 1 7 pcsel $end
$var wire 1 < jSel $end
$upscope $end
$scope module id $end
$var wire 1 # clk $end
$var wire 1 ! dgnd $end
$var wire 1 " dvdd $end
$var wire 1 - rfen $end
$var wire 1 , selB $end
$var wire 2 Y selType [1:0] $end
$var wire 2 Z selOp [1:0] $end
$var wire 2 [ rd [1:0] $end
$var wire 2 \ rb [1:0] $end
$var wire 2 ] ra [1:0] $end
$var wire 4 ^ opcode [3:0] $end
$var wire 1 : msel $end
$var wire 1 9 memwen $end
$var wire 1 < jsel $end
$var wire 16 _ instr [15:0] $end
$var wire 1 > cbzsel $end
$var wire 8 ` c [7:0] $end
$upscope $end
$scope module mem $end
$var wire 16 a addressA [15:0] $end
$var wire 16 b addressB [15:0] $end
$var wire 16 c dataInA [15:0] $end
$var wire 1 ! dgnd $end
$var wire 1 " dvdd $end
$var wire 1 ) rstz $end
$var wire 1 % writeEnableA $end
$var wire 1 9 writeEnableB $end
$var wire 16 d nextAddrB [15:0] $end
$var wire 16 e nextAddrA [15:0] $end
$var wire 16 f dataOutB [15:0] $end
$var wire 16 g dataOutA [15:0] $end
$var wire 16 h dataInB [15:0] $end
$scope begin $ivl_for_loop0 $end
$var integer 32 i i [31:0] $end
$upscope $end
$upscope $end
$scope module rf $end
$var wire 1 # clk $end
$var wire 16 j data [15:0] $end
$var wire 1 ! dgnd $end
$var wire 1 " dvdd $end
$var wire 1 - en $end
$var wire 2 k ra [1:0] $end
$var wire 2 l rb [1:0] $end
$var wire 2 m rd [1:0] $end
$var wire 1 & rstz $end
$var wire 16 n opD [15:0] $end
$var wire 16 o opB [15:0] $end
$var wire 16 p opA [15:0] $end
$var parameter 32 q NREGISTERS $end
$var parameter 32 r WIDTH $end
$scope begin $ivl_for_loop1 $end
$var integer 32 s i [31:0] $end
$upscope $end
$upscope $end
$upscope $end
$scope begin $ivl_for_loop2 $end
$var integer 32 t i [31:0] $end
$upscope $end
$scope task program $end
$upscope $end
$upscope $end
$enddefinitions $end
$comment Show the parameter values. $end
$dumpall
b10000 r
b100 q
b1000000000000000 B
$end
#0
$dumpvars
bx t
bx s
bx p
bx o
bx n
bx m
bx l
bx k
bx j
bx i
bx h
bx g
bx f
bx e
bx d
b0 c
bx b
bx a
bx `
bx _
bx ^
bx ]
bx \
bx [
bx Z
bx Y
bx X
bx W
bx V
bx U
bx T
bx S
bx R
bx Q
bx P
b0x O
bx N
bx M
bx L
bx K
bx J
bx I
bx H
bx G
bx F
bx E
bx D
bx C
bx A
bx @
x?
x>
bx =
x<
bx ;
x:
x9
bx 8
x7
bx 6
bx 5
bx 4
bx 3
bx 2
bx 1
bx 0
bx /
bx .
x-
x,
bx +
bx *
1)
b0 (
x'
1&
1%
b0 $
0#
z"
z!
$end
#5000
b100 s
1#
#10000
b100000000000000 i
0)
0#
0&
#15000
b0 ;
b0 f
b0 *
b0 j
1,
b1 d
b0 A
b0 Q
b0 b
b0 P
b0 T
b0 N
b0 O
b0 R
b0 I
b1111111111111111 F
b0 G
b0 E
1-
b1000000000000010 8
b0 H
b0 V
b0 M
b0 L
b0 U
b0 S
b0 3
b0 D
b0 4
b0 o
b0 5
b0 X
b0 p
1?
b0 1
b0 W
b0 h
b0 n
b0 +
b0 J
b0 Y
b0 6
b0 K
b0 Z
07
0'
b0 2
b0 @
b0 `
b0 /
b0 \
b0 l
b0 0
b0 ]
b0 k
b0 .
b0 [
b0 m
09
0<
0:
0>
b0 ^
b0 =
b0 _
b0 g
b1000000000000001 e
b1000000000000000 C
b1000000000000000 a
b100 s
1#
#20000
1)
0#
0%
1&
#25000
b1000000000000100 8
b1000000000000011 e
b1000000000000010 C
b1000000000000010 a
b100 s
1#
#30000
b100000000000000 i
0)
0#
1%
0&
#35000
b1000000000000010 8
b1000000000000001 e
b1000000000000000 C
b1000000000000000 a
b100 s
1#
#40000
1)
0#
1&
#45000
b1000000000000100 8
b1000000000000011 e
b1000000000000010 C
b1000000000000010 a
b100 s
1#
#50000
0#
b1010000000000001 $
b1010000000000001 (
b1010000000000001 c
#55000
b1 *
b1 j
b10 d
b1 A
b1 Q
b1 b
b1 R
b1111111111111111 P
b1 G
b1 I
b1 N
b1 O
b1 H
b1 V
b1 U
b1 S
b1 3
b1 D
b10 +
b10 J
b10 Y
b10 6
b10 K
b10 Z
b1 2
b1 @
b1 `
b1 /
b1 \
b1 l
b1010 ^
b1010000000000001 =
b1010000000000001 _
b1010000000000001 g
b1000000000000110 8
b1000000000000101 e
b1000000000000100 C
b1000000000000100 a
b100 s
1#
#60000
0#
b1010010000000010 $
b1010010000000010 (
b1010010000000010 c
#65000
b11 G
b1 .
b1 [
b1 m
b10 *
b10 j
b11 d
b10 A
b10 Q
b10 b
b10 N
1,
b1111111111111110 P
b10 T
b10 H
b0 L
b10 3
b10 D
b0 4
b0 o
b10 +
b10 J
b10 Y
b10 6
b10 K
b10 Z
b11 R
b1 O
b11 I
b1111111111111110 F
b0 E
b10 2
b10 @
b10 `
b10 /
b10 \
b10 l
b1010 ^
b11 S
b11 U
b10 M
b11 V
b1 5
b1 X
b1 p
1?
b0 1
b0 W
b0 h
b0 n
b1000000000001000 8
b1010010000000010 =
b1010010000000010 _
b1010010000000010 g
b1000000000000111 e
b1000000000000110 C
b1000000000000110 a
b100 s
1#
#70000
0#
b1010110001111111 $
b1010110001111111 (
b1010110001111111 c
#75000
b1111111 *
b1111111 j
b1 E
b10000000 d
b1111111 A
b1111111 Q
b1111111 b
1,
b1111111111111110 P
b1111111 T
b1111111 G
b1111110 I
b1111111 N
b1 O
b10000000 R
b1111111 H
b10000000 V
b1111111 M
b0 L
b10000000 U
b10000000 S
b1111111 3
b1111111 D
b0 4
b0 o
b10 +
b10 J
b10 Y
b10 6
b10 K
b10 Z
1?
b0 1
b0 W
b0 h
b0 n
b1111111 2
b1111111 @
b1111111 `
b11 /
b11 \
b11 l
b1010 ^
b11 .
b11 [
b11 m
b1000000000001010 8
b1010110001111111 =
b1010110001111111 _
b1010110001111111 g
b1000000000001001 e
b1000000000001000 C
b1000000000001000 a
b100 s
1#
#80000
0#
b10111100000011 $
b10111100000011 (
b10111100000011 c
#85000
b1111111110000000 F
b1111111 5
b1111111 X
b1111111 p
b11 0
b11 ]
b11 k
b11111100000001 *
b11111100000001 j
b11111100000010 d
b11111100000001 A
b11111100000001 Q
b11111100000001 b
0,
b1111111110000000 P
b11111100000001 T
b1111111 E
b1111111 G
b0 I
b1111111 N
b0 O
b11111110 R
b1111111 H
b11111110 V
b11111100000001 M
b0 L
b11111110 U
b11111110 S
b1111111 3
b1111111 D
b1111111 4
b1111111 o
0?
b1111111 1
b1111111 W
b1111111 h
b1111111 n
b0 +
b0 J
b0 Y
b10 6
b10 K
b10 Z
b11 2
b11 @
b11 `
b11 /
b11 \
b11 l
b11 .
b11 [
b11 m
b10 ^
b1000000000001100 8
b10111100000011 =
b10111100000011 _
b10111100000011 g
b1000000000001011 e
b1000000000001010 C
b1000000000001010 a
b100 s
1#
#90000
0#
b10000000000001 $
b10000000000001 (
b10000000000001 c
#95000
b10 *
b10 j
b0 L
b11 d
b10 A
b10 Q
b10 b
0,
b11 G
b10 N
b1111111111111110 P
b10 T
b10 H
b10 3
b10 D
b11 R
b1 O
b11 I
b1111111111111110 F
b0 E
b10 4
b10 o
b1 1
b1 W
b1 h
b1 n
b11 S
b11 U
b10 M
b11 V
b1 5
b1 X
b1 p
b10 6
b10 K
b10 Z
b1 /
b1 \
b1 l
b1 2
b1 @
b1 `
b0 .
b0 [
b0 m
b0 0
b0 ]
b0 k
b10 ^
b1000000000001110 8
b10000000000001 =
b10000000000001 _
b10000000000001 g
b1000000000001101 e
b1000000000001100 C
b1000000000001100 a
b100 s
1#
#100000
0#
b1100100000000011 $
b1100100000000011 (
b1100100000000011 c
#105000
1?
b11111100000001 4
b11111100000001 o
b11 +
b11 J
b11 Y
b10 .
b10 [
b10 m
b11111100000001 H
b0 L
b11111100000001 3
b11111100000001 D
b1 *
b1 j
0,
b10 d
b1 A
b1 Q
b1 b
b11111100000011 N
b0 P
b11111100000011 T
b0 6
b0 K
b0 Z
b1 R
b1 O
b11111100000011 I
b1111111111111101 F
b11111100000011 G
b0 E
b11 2
b11 @
b11 `
b11 /
b11 \
b11 l
b1100 ^
b11111100000011 S
b11111100000011 U
b111111000000010 M
b11111100000011 V
b10 5
b10 X
b10 p
b0 1
b0 W
b0 h
b0 n
b1000000000010000 8
b1100100000000011 =
b1100100000000011 _
b1100100000000011 g
b1000000000001111 e
b1000000000001110 C
b1000000000001110 a
b100 s
1#
#110000
0#
b1101101000000001 $
b1101101000000001 (
b1101101000000001 c
#115000
b1111111111111110 F
b1 5
b1 X
b1 p
b1 6
b1 K
b1 Z
b10 0
b10 ]
b10 k
b1 P
b0 L
b0 R
1,
b0 *
b0 j
b1 E
b1 G
b0 I
b10 T
b10 N
b0 O
b1 d
b0 A
b0 Q
b0 b
b1 H
b10 V
b1 M
b10 U
b10 S
b1 3
b1 D
b10 4
b10 o
0?
b1 1
b1 W
b1 h
b1 n
b11 +
b11 J
b11 Y
b1 2
b1 @
b1 `
b1 /
b1 \
b1 l
b10 .
b10 [
b10 m
b1101 ^
b1000000000010010 8
b1101101000000001 =
b1101101000000001 _
b1101101000000001 g
b1000000000010001 e
b1000000000010000 C
b1000000000010000 a
b100 s
1#
#120000
0#
b1110100111111000 $
b1110100111111000 (
b1110100111111000 c
#125000
17
1'
1?
b1111111111111010 R
b1 O
0-
1>
b1111111111110000 T
b1111111111111000 N
b1111111111111010 *
b1111111111111010 j
b1111111111111101 P
b1111111111111011 d
b1111111111111010 A
b1111111111111010 Q
b1111111111111010 b
b1111111111111010 I
b1111111111111101 F
b1111111111111010 G
b0 E
1,
b1111111111111000 H
b1111111111111000 3
b1111111111111000 D
b1111111111111010 S
b1111111111111010 U
b0 L
b1111111111110000 M
b1111111111111010 V
b10 5
b10 X
b10 p
b0 1
b0 W
b0 h
b0 n
b11 +
b11 J
b11 Y
b10 6
b10 K
b10 Z
b1111111111111000 2
b11111000 @
b11111000 `
b0 /
b0 \
b0 l
b1 0
b1 ]
b1 k
b10 .
b10 [
b10 m
b1110 ^
b1000000000001100 8
b1110100111111000 =
b1110100111111000 _
b1110100111111000 g
b1000000000010011 e
b1000000000010010 C
b1000000000010010 a
b100 s
1#
#130000
0#
b11111111 $
b11111111 (
b11111111 c
#135000
b11111100000001 4
b11111100000001 o
b11 /
b11 \
b11 l
b10 E
b1 *
b1 j
b10 d
b1 A
b1 Q
b1 b
b10 P
b1 T
b1111111111111111 G
b1111111111111101 I
b1 N
b1 O
b1 R
1,
1-
07
b1111111111111111 H
b1 V
b1111111111111110 M
b0 L
b1 U
b1 S
b1111111111111111 3
b1111111111111111 D
0?
b10 1
b10 W
b10 h
b10 n
b0 +
b0 J
b0 Y
b0 6
b0 K
b0 Z
0'
b1111111111111111 2
b11111111 @
b11111111 `
b0 .
b0 [
b0 m
b0 0
b0 ]
b0 k
0>
b0 ^
b1000000000010110 8
b11111111 =
b11111111 _
b11111111 g
b1000000000010101 e
b1000000000010100 C
b1000000000010100 a
b100 s
1#
#140000
0#
0&
0%
#145000
b0 *
b0 j
b0 R
b1 d
b0 A
b0 Q
b0 b
b0 P
b0 G
b0 O
b0 H
b0 3
b0 D
b0 4
b0 o
b0 N
b0 T
b0 I
b1111111111111111 F
b0 E
b0 2
b0 @
b0 `
b0 /
b0 \
b0 l
b0 S
b0 U
b0 M
b0 V
b0 5
b0 X
b0 p
1?
b0 1
b0 W
b0 h
b0 n
b1000000000000010 8
b0 =
b0 _
b0 g
b1000000000000001 e
b1000000000000000 C
b1000000000000000 a
b100 s
1#
#150000
0#
b0 t
1&
#155000
b1000000000000100 8
b1000000000000011 e
b1000000000000010 C
b1000000000000010 a
b100 s
1#
#160000
0#
b1 t
#165000
b1 *
b1 j
b10 d
b1 A
b1 Q
b1 b
b1 R
b1111111111111111 P
b1 G
b1 I
b1 N
b1 O
b1 H
b1 V
b1 U
b1 S
b1 3
b1 D
b10 +
b10 J
b10 Y
b10 6
b10 K
b10 Z
b1 2
b1 @
b1 `
b1 /
b1 \
b1 l
b1010 ^
b1000000000000110 8
b1010000000000001 =
b1010000000000001 _
b1010000000000001 g
b1000000000000101 e
b1000000000000100 C
b1000000000000100 a
b100 s
1#
#170000
0#
b10 t
#175000
b10 *
b10 j
b11 d
b10 A
b10 Q
b10 b
b1111111111111110 P
b11 G
b10 N
b10 T
b10 H
b10 3
b10 D
b11 R
b1 O
b11 I
b1111111111111110 F
b0 E
b10 2
b10 @
b10 `
b10 /
b10 \
b10 l
b1 .
b1 [
b1 m
b11 S
b11 U
b10 M
b11 V
b1 5
b1 X
b1 p
1?
b0 1
b0 W
b0 h
b0 n
b1000000000001000 8
b1010010000000010 =
b1010010000000010 _
b1010010000000010 g
b1000000000000111 e
b1000000000000110 C
b1000000000000110 a
b100 s
1#
#180000
0#
b11 t
#185000
b1111111 *
b1111111 j
b10000000 d
b1111111 A
b1111111 Q
b1111111 b
b1111111 T
b1 E
b1111111 G
b1111110 I
b1111111 N
b10000000 R
b1111111 H
b10000000 V
b1111111 M
b10000000 U
b10000000 S
b1111111 3
b1111111 D
1?
b0 1
b0 W
b0 h
b0 n
b1111111 2
b1111111 @
b1111111 `
b11 /
b11 \
b11 l
b11 .
b11 [
b11 m
b1000000000001010 8
b1010110001111111 =
b1010110001111111 _
b1010110001111111 g
b1000000000001001 e
b1000000000001000 C
b1000000000001000 a
b100 s
1#
#190000
0#
b100 t
#195000
b11111100000001 *
b11111100000001 j
b11111100000010 d
b11111100000001 A
b11111100000001 Q
b11111100000001 b
b1111111110000000 P
b11111100000001 T
0,
b1111111 N
b11111110 R
b0 O
b0 I
b1111111110000000 F
b1111111 E
b1111111 4
b1111111 o
0?
b1111111 1
b1111111 W
b1111111 h
b1111111 n
b1111111 H
b0 L
b1111111 3
b1111111 D
b11111110 S
b11111110 U
b11111100000001 M
b11111110 V
b1111111 5
b1111111 X
b1111111 p
b0 +
b0 J
b0 Y
b11 2
b11 @
b11 `
b11 0
b11 ]
b11 k
b10 ^
b1000000000001100 8
b10111100000011 =
b10111100000011 _
b10111100000011 g
b1000000000001011 e
b1000000000001010 C
b1000000000001010 a
b100 s
1#
#200000
0#
b101 t
#205000
b10 *
b10 j
b11 d
b10 A
b10 Q
b10 b
b1111111111111110 P
b11 G
b10 N
b10 T
b10 H
b10 3
b10 D
b11 R
b1 O
b11 I
b1111111111111110 F
b0 E
b10 4
b10 o
b1 1
b1 W
b1 h
b1 n
b11 S
b11 U
b10 M
b11 V
b1 5
b1 X
b1 p
b1 /
b1 \
b1 l
b1 2
b1 @
b1 `
b0 .
b0 [
b0 m
b0 0
b0 ]
b0 k
b1000000000001110 8
b10000000000001 =
b10000000000001 _
b10000000000001 g
b1000000000001101 e
b1000000000001100 C
b1000000000001100 a
b100 s
1#
#210000
0#
b110 t
#215000
b1 *
b1 j
b10 d
b1 A
b1 Q
b1 b
b11111100000001 H
b11111100000001 3
b11111100000001 D
1?
b11111100000011 N
b0 P
b11111100000001 4
b11111100000001 o
b11111100000011 T
b11 +
b11 J
b11 Y
b0 6
b0 K
b0 Z
b1 R
b1 O
b11111100000011 I
b1111111111111101 F
b11111100000011 G
b0 E
b11 2
b11 @
b11 `
b11 /
b11 \
b11 l
b10 .
b10 [
b10 m
b1100 ^
b11111100000011 S
b11111100000011 U
b111111000000010 M
b11111100000011 V
b10 5
b10 X
b10 p
b0 1
b0 W
b0 h
b0 n
b1000000000010000 8
b1100100000000011 =
b1100100000000011 _
b1100100000000011 g
b1000000000001111 e
b1000000000001110 C
b1000000000001110 a
b100 s
1#
#220000
0#
b111 t
#225000
b0 *
b0 j
b1 d
b0 A
b0 Q
b0 b
b1 P
b0 R
b1 H
b0 L
b1 3
b1 D
b10 4
b10 o
b0 O
b10 N
b10 T
b0 I
b1111111111111110 F
b1 G
b1 E
1,
0?
b1 1
b1 W
b1 h
b1 n
b10 S
b10 U
b1 M
b10 V
b1 5
b1 X
b1 p
b1 6
b1 K
b1 Z
b1 2
b1 @
b1 `
b1 /
b1 \
b1 l
b10 0
b10 ]
b10 k
b1101 ^
b1000000000010010 8
b1101101000000001 =
b1101101000000001 _
b1101101000000001 g
b1000000000010001 e
b1000000000010000 C
b1000000000010000 a
b100 s
1#
#230000
0#
b1000 t
