testbench/program.v
`define NUM_INSTRUCTIONS 12

task program(); begin
	#10 instr = 16'hA408;
	#10 instr = 16'hA802;
	#10 instr = 16'h1102;
	#10 instr = 16'h2102;
	#10 instr = 16'h3102;
	#10 instr = 16'h4102;
	#10 instr = 16'h5102;
	#10 instr = 16'h6100;
	#10 instr = 16'h7102;
end
endtask

rtl/MEM12b4bA.v
// essentially, this memory block is a transparent register bank

module MEM12b4bA (
    input [15:0] addressA,
    input [15:0] addressB,
    input [15:0] dataInA,
    input [15:0] dataInB,
    input writeEnableA,
    input writeEnableB,
	input clk,
    output [15:0] dataOutA,
    output [15:0] dataOutB,
    inout dvdd,
    inout dgnd
);

// Memory array declaration
reg [7:0] memory [0:65535];

wire [15:0] nextAddrA, nextAddrB;

integer i;

assign nextAddrA = addressA + 1;
assign nextAddrB = addressB + 1;

// Memory Write Operations
always @(negedge clk)
begin
		if (writeEnableA == 1'b1) begin
			memory[addressA] <= dataInA[15:8];
			memory[nextAddrA] <= dataInA[7:0];
		end
		if (writeEnableB == 1'b1) begin
			memory[addressB] <= dataInB[15:8];
			memory[nextAddrB] <= dataInB[7:0];
		end
end

// Memory Read Operations
assign dataOutA = {memory[addressA], memory[nextAddrA]};
assign dataOutB = {memory[addressB], memory[nextAddrB]};

endmodule

rtl/BC16bA.v
module BC16bA (
	input jSel,
	input cbz,
	output pcsel,
	inout dvdd,
	inout dgnd
);

assign pcsel = cbz | jSel;

endmodule

rtl/ALU16bA.v
module ALU16bA (
	input [15:0] opA, // Operand A (RA)
	input [15:0] opB, // Operand B (RB or C)
	input [15:0] opD, // Operand D (RD - read only)
	input [1:0] selType, // Type Select: Arithmetic, Logic, LD/ST, Conditional
	input [1:0] selOp, // Operation Select (Arithm: add, mul, rsa; Logic: and, or, not, xor; ...)
	output [15:0] res, // ALU result
	output cbz, // conditional branch zero flag
	inout dvdd,
	inout dgnd
);

wire [15:0] radd;
wire [15:0] rmul;
wire [15:0] rsra;
wire [15:0] ratm;

wire [15:0] rrand;
wire [15:0] ror;
wire [15:0] rnot;
wire [15:0] rxor;
wire [15:0] rlog;

wire [15:0] radr;
wire [15:0] rset;
wire [15:0] rmem;

wire [15:0] rlt;
wire [15:0] rbj; // RA + C for branches and jumps
wire [15:0] rcnd;

// Arithmetic Operations
assign radd = opA + opB;
assign rmul = opA * opB;
assign rsra = opA >> opB;

assign ratm = selOp[1] ? (selOp[0] ? rsra : rmul) : radd;

// Logic Operations
assign rrand = opA & opB;
assign ror = opA | opB;
assign rnot = ~opA;
assign rxor = opA ^ opB;

assign rlog = selOp[1] ? (selOp[0] ? rxor : rnot) : (selOp[0] ? ror : rrand);

// LD/ST Operations
assign radr = opA + opB;
assign rset = opB;

assign rmem = selOp[1] ? rset : radr; // if 1X => rset, else its LD/ST

// Conditionals
assign rlt = opA < opB ? 16'h0001 : 16'b0;
assign rbj = opA + opB;

assign rcnd = selOp[1] ? rbj : rlt;

// ALU Output
assign res = selType[1] ? ( selType[0] ? rcnd : rmem ) : (selType[0] ? rlog : ratm);
assign cbz = opD == 16'b0; // if opD == 0 => cbz = 1 else cbz = 0

endmodule

rtl/RF16bA.v
module RF16bA (
	input [1:0] rd,
	input [1:0] ra,
	input [1:0] rb,
	input [15:0] data,
        input clk,
	input rstz,
	input en,
	output [15:0] opA,
	output [15:0] opB,
	output [15:0] opD,
	inout dvdd,
	inout dgnd
);

parameter NREGISTERS = 4;
parameter WIDTH = 16;

reg [(WIDTH-1):0] r[0:(NREGISTERS-1)];

integer i;

// Define Registers R0 - R3
always @(posedge clk)
begin
	for (i = 0; i < NREGISTERS; i = i +1) begin
		if (!rstz) 
			r[i] <= 0;
		else if ((rd == i) & en)
			r[i] <= data;
		else
			r[i] = r[i];
	end
end

assign opA = ra == 2'b0 ? r[0] : (ra == 2'b01 ? r[1] : (ra == 2'b10 ? r[2] : r[3]));
assign opB = rb == 2'b0 ? r[0] : (rb == 2'b01 ? r[1] : (rb == 2'b10 ? r[2] : r[3]));
assign opD = rd == 2'b0 ? r[0] : (rd == 2'b01 ? r[1] : (rd == 2'b10 ? r[2] : r[3]));

endmodule

rtl/ID16bA.v
module ID16bA (
	input [15:0] instr, // 16 bit instruction to be decoded
        input clk, // system clock
	output [1:0] rd, // Destination Register D ID
	output [1:0] ra, // Operand Register A ID
	output [1:0] rb, // Operand Register B ID
	output [7:0] c, // Immediate / Constant
	output [1:0] selType, // muxsel for operation type (arithm, logic, mem, conditional / flow control)
	output [1:0] selOp, // muxsel for operation of a given type (ex: arithm -> adc, add, mul, sra)
	output selB, // muxsel for second operand (Register B or Constant C)
	output jsel, // jump select
	output cbzsel, // cbz select
	output msel, // mem op select (high if instruction is a LD)
	output memwen, // memory write enable (high if instruction is a store)
	output rfen, // register file write enable (high if instruction writes to a register)
	inout dvdd, // module digital supply
	inout dgnd // module digital ground
);

// instr = [opcode(3:0), rd(1:0), ra(1:0), rb(1:0) / c(7:0)]

wire [3:0] opcode;

assign opcode = instr[15:12];
assign rd = instr[11:10];
assign ra = instr[9:8];
assign rb = instr[1:0];
assign c = instr[7:0];
// selB = 1 if instruction is ADC(0), LD(8), ST(9), SET(A), LTC(D), CBZ(E) or
// JMP(F)
assign selB = opcode == 4'h0 | opcode[3:1] == 3'b100 | opcode == 4'ha | opcode == 4'hd | opcode[3:1] == 3'b111;

assign selType = opcode[3:2];
assign selOp = opcode[1:0];

assign memwen = opcode == 4'h9; // instr is ST
assign rfen = (opcode != 4'h9 & opcode != 4'he & opcode != 4'hf); // instr is not ST neither CBZ nor JMP
assign jsel = opcode == 4'hf; // instr is JMP
assign msel = opcode == 4'h8; // instr is LD
assign cbzsel = opcode == 4'he; // instr is CBZ

endmodule

rtl/MAS16bA.v
module MAS16bA (
	input [15:0] pg_instr, // program instruction => stored in memory in programming mode
	input pg, // programming mode (for writing the program to memory)
        input clk,
	input rstz,
	inout dvdd,
	inout dgnd
);

// Base Instruction Mem Address
parameter instrAddr = 16'h8000;

wire [15:0] instr;
wire [15:0] opa;
wire [15:0] opb;
wire [15:0] opc;
wire [15:0] opd;
wire [15:0] opb_alu;
wire [15:0] alu_res;
wire [15:0] mem_out;
wire [7:0] c;
wire [15:0] wbdata;
wire [1:0] ra, rb, rd, type, op;
wire selB;
wire jsel;
wire msel;
wire mwen;
wire wdataen;
wire rfen;
wire cbzsel;
wire cbz_flag;
wire cbz;
wire nextpc_flag;

wire [15:0] nextpc;
reg [15:0] pc;

assign opc = {{8{c[7]}}, c};

ID16bA id(
	.instr(instr),
	.clk(clk),
	.rd(rd),
	.ra(ra),
	.rb(rb),
	.c(c),
	.selType(type),
	.selOp(op),
	.selB(selB),
	.jsel(jsel),
	.msel(msel),
	.cbzsel(cbzsel),
	.memwen(mwen),
	.rfen(rfen),
	.dvdd(dvdd),
	.dgnd(dgnd)
);

RF16bA rf(
	.rd(rd),
	.ra(ra),
	.rb(rb),
	.data(wbdata), // write-back data
	.clk(clk),
	.rstz(rstz),
	.en(rfen),
	.opA(opa),
	.opB(opb),
	.opD(opd),
	.dvdd(dvdd),
	.dgnd(dgnd)	
);

assign opb_alu = selB ? opc : opb; // ALUs operand B will be C if ADC, LD, ST, ..., otherwise RB

ALU16bA alu(
	.opA(opa),
	.opB(opb_alu),
	.opD(opd),
	.selType(type),
	.selOp(op),
	.res(alu_res),
	.cbz(cbz_flag),
	.dvdd(dvdd),
	.dgnd(dgnd)
);

assign cbz = cbz_flag & cbzsel;

BC16bA bc(
	.jSel(jsel),
	.cbz(cbz),
	.pcsel(nextpc_flag),
	.dvdd(dvdd),
	.dgnd(dgnd)
);

assign wdataen = !pg & mwen;

MEM12b4bA mem(
	.addressA(pc), // port A is for instructions => address A = PC
	.addressB(alu_res), // on memory operations, the ALU result is the memory address
	.dataInA(pg_instr),
	.dataInB(opd),
	.writeEnableA(pg),
	.writeEnableB(wdataen),
	.clk(clk),
	.dataOutA(instr),
	.dataOutB(mem_out),
	.dvdd(dvdd),
	.dgnd(dgnd)
);

// Write-Back
assign wbdata = msel ? mem_out : alu_res;


assign nextpc = nextpc_flag ? pc + alu_res : pc + 2; // add 2B, since each instr. is 2B (except if CBZ/JMP)

// Program Count
always @(posedge clk) begin
	if (rstz == 0) begin
		pc <= instrAddr;
	end
	else if (pg == 0)
		pc <= nextpc;
	else
		pc <= pc + 2; // fully sequential on programming mode
end

endmodule

testbench/MAS16bA_tb.v
`timescale 1ns / 1ps

module MAS16bA_tb;

reg [15:0] instr;
reg clk, rstz, pg;
wire dvdd, dgnd;

MAS16bA uut (
	.pg_instr(instr),
	.pg(pg),
	.clk(clk),
	.rstz(rstz),
	.dvdd(dvdd),
	.dgnd(dgnd)
);

`include "program.v"

initial
begin
$dumpfile("dump.vcd");
$dumpvars(0, MAS16bA_tb);

// Shows the memory
/*for (integer j = 0; j < 65536; j = j+1) begin
		$dumpvars(0, uut.mem.memory[j]);
	end*/

clk = 0;
rstz = 1;
pg = 1;
instr = 16'h0000;
#10 rstz = 0;
#10 rstz = 1; pg = 0;
#10 rstz = 0; pg = 1;
#10 rstz = 1;

program();

/*instr = 16'h0001;
#10 instr = 16'h0502;
#10 instr = 16'h0a03;
#10 instr = 16'h0f04;
#10 instr = 16'h2e03;
#10 instr = 16'ha000;
#10 instr = 16'hf0fe;*/

#10 instr = 16'ha000;
#10 instr = 16'hf000; // end program

#10 pg = 0; rstz = 0;
#10 rstz = 1;
for (integer i = 0; i < `NUM_INSTRUCTIONS; i = i + 1) begin
	#10 $display("instr: %h; R0 = %1d, R1 = %1d, R2 = %1d, R3 = %1d",uut.instr, uut.rf.r[0], uut.rf.r[1], uut.rf.r[2], uut.rf.r[3]);
end

$finish;
end

always #5 clk = ~clk;
endmodule

testbench/dump.vcd
$date
	Sun May 19 18:39:45 2024
$end
$version
	Icarus Verilog
$end
$timescale
	1ps
$end
$scope module MAS16bA_tb $end
$var wire 1 ! dgnd $end
$var wire 1 " dvdd $end
$var reg 1 # clk $end
$var reg 16 $ instr [15:0] $end
$var reg 1 % pg $end
$var reg 1 & rstz $end
$scope module uut $end
$var wire 1 ' cbz $end
$var wire 1 # clk $end
$var wire 1 ! dgnd $end
$var wire 1 " dvdd $end
$var wire 1 % pg $end
$var wire 16 ( pg_instr [15:0] $end
$var wire 1 & rstz $end
$var wire 1 ) wdataen $end
$var wire 16 * wbdata [15:0] $end
$var wire 2 + type [1:0] $end
$var wire 1 , selB $end
$var wire 1 - rfen $end
$var wire 2 . rd [1:0] $end
$var wire 2 / rb [1:0] $end
$var wire 2 0 ra [1:0] $end
$var wire 16 1 opd [15:0] $end
$var wire 16 2 opc [15:0] $end
$var wire 16 3 opb_alu [15:0] $end
$var wire 16 4 opb [15:0] $end
$var wire 16 5 opa [15:0] $end
$var wire 2 6 op [1:0] $end
$var wire 1 7 nextpc_flag $end
$var wire 16 8 nextpc [15:0] $end
$var wire 1 9 mwen $end
$var wire 1 : msel $end
$var wire 16 ; mem_out [15:0] $end
$var wire 1 < jsel $end
$var wire 16 = instr [15:0] $end
$var wire 1 > cbzsel $end
$var wire 1 ? cbz_flag $end
$var wire 8 @ c [7:0] $end
$var wire 16 A alu_res [15:0] $end
$var parameter 16 B instrAddr $end
$var reg 16 C pc [15:0] $end
$scope module alu $end
$var wire 1 ! dgnd $end
$var wire 1 " dvdd $end
$var wire 16 D opB [15:0] $end
$var wire 16 E rnot [15:0] $end
$var wire 16 F ror [15:0] $end
$var wire 16 G rrand [15:0] $end
$var wire 16 H rset [15:0] $end
$var wire 16 I rxor [15:0] $end
$var wire 2 J selType [1:0] $end
$var wire 2 K selOp [1:0] $end
$var wire 16 L rsra [15:0] $end
$var wire 16 M rmul [15:0] $end
$var wire 16 N rmem [15:0] $end
$var wire 16 O rlt [15:0] $end
$var wire 16 P rlog [15:0] $end
$var wire 16 Q res [15:0] $end
$var wire 16 R rcnd [15:0] $end
$var wire 16 S rbj [15:0] $end
$var wire 16 T ratm [15:0] $end
$var wire 16 U radr [15:0] $end
$var wire 16 V radd [15:0] $end
$var wire 16 W opD [15:0] $end
$var wire 16 X opA [15:0] $end
$var wire 1 ? cbz $end
$upscope $end
$scope module bc $end
$var wire 1 ' cbz $end
$var wire 1 ! dgnd $end
$var wire 1 " dvdd $end
$var wire 1 7 pcsel $end
$var wire 1 < jSel $end
$upscope $end
$scope module id $end
$var wire 1 # clk $end
$var wire 1 ! dgnd $end
$var wire 1 " dvdd $end
$var wire 1 - rfen $end
$var wire 1 , selB $end
$var wire 2 Y selType [1:0] $end
$var wire 2 Z selOp [1:0] $end
$var wire 2 [ rd [1:0] $end
$var wire 2 \ rb [1:0] $end
$var wire 2 ] ra [1:0] $end
$var wire 4 ^ opcode [3:0] $end
$var wire 1 : msel $end
$var wire 1 9 memwen $end
$var wire 1 < jsel $end
$var wire 16 _ instr [15:0] $end
$var wire 1 > cbzsel $end
$var wire 8 ` c [7:0] $end
$upscope $end
$scope module mem $end
$var wire 16 a addressA [15:0] $end
$var wire 16 b addressB [15:0] $end
$var wire 1 # clk $end
$var wire 16 c dataInA [15:0] $end
$var wire 1 ! dgnd $end
$var wire 1 " dvdd $end
$var wire 1 % writeEnableA $end
$var wire 1 ) writeEnableB $end
$var wire 16 d nextAddrB [15:0] $end
$var wire 16 e nextAddrA [15:0] $end
$var wire 16 f dataOutB [15:0] $end
$var wire 16 g dataOutA [15:0] $end
$var wire 16 h dataInB [15:0] $end
$upscope $end
$scope module rf $end
$var wire 1 # clk $end
$var wire 16 i data [15:0] $end
$var wire 1 ! dgnd $end
$var wire 1 " dvdd $end
$var wire 1 - en $end
$var wire 2 j ra [1:0] $end
$var wire 2 k rb [1:0] $end
$var wire 2 l rd [1:0] $end
$var wire 1 & rstz $end
$var wire 16 m opD [15:0] $end
$var wire 16 n opB [15:0] $end
$var wire 16 o opA [15:0] $end
$var parameter 32 p NREGISTERS $end
$var parameter 32 q WIDTH $end
$var integer 32 r i [31:0] $end
$upscope $end
$upscope $end
$scope begin $ivl_for_loop0 $end
$var integer 32 s i [31:0] $end
$upscope $end
$scope task program $end
$upscope $end
$upscope $end
$enddefinitions $end
$comment Show the parameter values. $end
$dumpall
b10000 q
b100 p
b1000000000000000 B
$end
#0
$dumpvars
bx s
bx r
bx o
bx n
bx m
bx l
bx k
bx j
bx i
bx h
bx g
bx f
bx e
bx d
b0 c
bx b
bx a
bx `
bx _
bx ^
bx ]
bx \
bx [
bx Z
bx Y
bx X
bx W
bx V
bx U
bx T
bx S
bx R
bx Q
bx P
b0x O
bx N
bx M
bx L
bx K
bx J
bx I
bx H
bx G
bx F
bx E
bx D
bx C
bx A
bx @
x?
x>
bx =
x<
bx ;
x:
x9
bx 8
x7
bx 6
bx 5
bx 4
bx 3
bx 2
bx 1
bx 0
bx /
bx .
x-
x,
bx +
bx *
0)
b0 (
x'
1&
1%
b0 $
0#
z"
z!
$end
#5000
b100 r
1#
#10000
0#
0&
#15000
b1111111111111111 E
b0 G
b0 5
b0 X
b0 o
b0 4
b0 n
1?
b0 1
b0 W
b0 h
b0 m
b1000000000000001 e
b1000000000000000 C
b1000000000000000 a
b100 r
1#
#20000
x)
0#
0%
1&
#25000
bx e
bx C
bx a
b100 r
1#
#30000
0)
0#
1%
0&
#35000
b1000000000000001 e
b1000000000000000 C
b1000000000000000 a
b100 r
1#
#40000
b0 *
b0 i
1,
b1 d
b0 A
b0 Q
b0 b
b0 P
b0 F
b0 I
b0 T
b0 N
b0 O
b0 R
1-
b1000000000000010 8
b0 H
b0 V
b0 M
b0 L
b0 U
b0 S
b0 3
b0 D
b0 +
b0 J
b0 Y
b0 6
b0 K
b0 Z
07
0'
b0 2
b0 @
b0 `
b0 /
b0 \
b0 k
b0 0
b0 ]
b0 j
b0 .
b0 [
b0 l
09
0<
0:
0>
b0 ^
b0 =
b0 _
b0 g
0#
1&
#45000
x,
bx d
bx A
bx Q
bx b
bx R
bx P
bx F
bx I
bx T
bx N
b0x O
bx H
bx V
bx M
bx L
bx U
bx S
bx 3
bx D
bx +
bx J
bx Y
bx 6
bx K
bx Z
x-
x7
bx *
bx i
x'
bx 8
bx 2
bx @
bx `
bx /
bx \
bx k
bx 0
bx ]
bx j
bx .
bx [
bx l
x9
x<
x:
x>
bx ^
b1000000000000011 e
bx =
bx _
bx g
b1000000000000010 C
b1000000000000010 a
b100 r
1#
#50000
b1001 d
b0 T
b1 O
b1000 R
b1000 *
b1000 i
b1000 V
b0 M
b0 L
b1000 U
b1000 S
b1000 A
b1000 Q
b1000 b
b1111111111111111 P
1,
b1000 F
b1000 I
b1000 N
1-
b1000000000000100 8
b1000 H
b1000 3
b1000 D
b10 +
b10 J
b10 Y
b10 6
b10 K
b10 Z
07
0'
b1000 2
b1000 @
b1000 `
b0 /
b0 \
b0 k
b0 0
b0 ]
b0 j
b1 .
b1 [
b1 l
09
0<
0:
0>
b1010 ^
b1010010000001000 =
b1010010000001000 _
b1010010000001000 g
0#
b1010010000001000 $
b1010010000001000 (
b1010010000001000 c
#55000
x,
bx d
bx A
bx Q
bx b
bx P
bx T
bx N
bx R
b0x O
bx I
b111111111111x111 E
bx F
b0x000 G
bx H
bx L
bx 3
bx D
b0x000 4
b0x000 n
bx S
bx U
bx M
bx V
b0x000 5
b0x000 X
b0x000 o
bx +
bx J
bx Y
bx 6
bx K
bx Z
x-
x7
bx *
bx i
x'
x?
b0x000 1
b0x000 W
b0x000 h
b0x000 m
bx 8
bx 2
bx @
bx `
bx /
bx \
bx k
bx 0
bx ]
bx j
bx .
bx [
bx l
x9
x<
x:
x>
bx ^
b1000000000000101 e
bx =
bx _
bx g
b1000000000000100 C
b1000000000000100 a
b100 r
1#
#60000
b11 d
b0 T
b1 O
b10 R
b10 *
b10 i
b10 V
b0 M
b0 L
b10 U
b10 S
b10 A
b10 Q
b10 b
b1111111111111111 P
1,
b10 N
b10 I
b1111111111111111 E
b10 F
b0 G
1-
b1000000000000110 8
b10 H
b10 3
b10 D
b0 4
b0 n
b0 5
b0 X
b0 o
1?
b0 1
b0 W
b0 h
b0 m
b10 +
b10 J
b10 Y
b10 6
b10 K
b10 Z
07
0'
b10 2
b10 @
b10 `
b10 /
b10 \
b10 k
b0 0
b0 ]
b0 j
b10 .
b10 [
b10 l
09
0<
0:
0>
b1010 ^
b1010100000000010 =
b1010100000000010 _
b1010100000000010 g
0#
b1010100000000010 $
b1010100000000010 (
b1010100000000010 c
#65000
x,
bx d
bx A
bx Q
bx b
bx P
bx T
bx N
bx R
b0x O
bx I
b111111111111x1x1 E
bx F
b0x0x0 G
bx H
bx 3
bx D
b0x0x0 4
b0x0x0 n
bx S
bx U
bx L
bx M
bx V
b0x0x0 5
b0x0x0 X
b0x0x0 o
x?
b0x0x0 1
b0x0x0 W
b0x0x0 h
b0x0x0 m
bx +
bx J
bx Y
bx 6
bx K
bx Z
x-
x7
bx *
bx i
x'
bx 8
bx 2
bx @
bx `
bx /
bx \
bx k
bx 0
bx ]
bx j
bx .
bx [
bx l
x9
x<
x:
x>
bx ^
b1000000000000111 e
bx =
bx _
bx g
b1000000000000110 C
b1000000000000110 a
b100 r
1#
#70000
b1010 *
b1010 i
0,
b1011 d
b1010 A
b1010 Q
b1010 b
b1010 P
b1010 T
b1010 N
b0 O
b0 R
b1010 I
b1111111111110111 E
b1010 F
b0 G
1-
b1000000000001000 8
b10 H
b1010 V
b10000 M
b10 L
b1010 U
b1010 S
b10 3
b10 D
b10 4
b10 n
b1000 5
b1000 X
b1000 o
1?
b0 1
b0 W
b0 h
b0 m
b0 +
b0 J
b0 Y
b1 6
b1 K
b1 Z
07
0'
b10 2
b10 @
b10 `
b10 /
b10 \
b10 k
b1 0
b1 ]
b1 j
b0 .
b0 [
b0 l
09
0<
0:
0>
b1 ^
b1000100000010 =
b1000100000010 _
b1000100000010 g
0#
b1000100000010 $
b1000100000010 (
b1000100000010 c
#75000
bx d
bx A
bx Q
bx b
bx P
bx R
bx H
bx 3
bx D
b0x O
bx N
bx T
bx I
b111111111111x1x1 E
bx F
b0x0x0 G
x'
x,
b0x0x0 4
b0x0x0 n
bx S
bx U
bx L
bx M
bx V
b0x0x0 5
b0x0x0 X
b0x0x0 o
bx +
bx J
bx Y
bx 6
bx K
bx Z
x-
x7
bx *
bx i
bx 8
bx 2
bx @
bx `
bx /
bx \
bx k
bx 0
bx ]
bx j
bx .
bx [
bx l
x9
x<
x:
x>
bx ^
x?
b0x0x0 1
b0x0x0 W
b0x0x0 h
b0x0x0 m
b1000000000001001 e
bx =
bx _
bx g
b1000000000001000 C
b1000000000001000 a
b100 r
1#
#80000
b10000 *
b10000 i
0,
b10001 d
b10000 A
b10000 Q
b10000 b
b1111111111110111 P
b10000 T
b10 N
b0 O
b1010 R
b1010 I
b1111111111110111 E
b1010 F
b0 G
1-
b1000000000001010 8
b10 H
b1010 V
b10000 M
b10 L
b1010 U
b1010 S
b10 3
b10 D
b10 4
b10 n
b1000 5
b1000 X
b1000 o
0?
b1010 1
b1010 W
b1010 h
b1010 m
b0 +
b0 J
b0 Y
b10 6
b10 K
b10 Z
07
0'
b10 2
b10 @
b10 `
b10 /
b10 \
b10 k
b1 0
b1 ]
b1 j
b0 .
b0 [
b0 l
09
0<
0:
0>
b10 ^
b10000100000010 =
b10000100000010 _
b10000100000010 g
0#
b10000100000010 $
b10000100000010 (
b10000100000010 c
#85000
bx d
bx A
bx Q
bx b
bx N
bx P
bx T
bx H
bx 3
bx D
bx R
b0x O
bx I
b11111111111xx1x1 E
bx F
b0xx0x0 G
x,
b0xx0x0 4
b0xx0x0 n
bx S
bx U
bx L
bx M
bx V
b0xx0x0 5
b0xx0x0 X
b0xx0x0 o
bx +
bx J
bx Y
bx 6
bx K
bx Z
x-
x7
bx *
bx i
x'
x?
b0xx0x0 1
b0xx0x0 W
b0xx0x0 h
b0xx0x0 m
bx 8
bx 2
bx @
bx `
bx /
bx \
bx k
bx 0
bx ]
bx j
bx .
bx [
bx l
x9
x<
x:
x>
bx ^
b1000000000001011 e
bx =
bx _
bx g
b1000000000001010 C
b1000000000001010 a
b100 r
1#
#90000
b10 *
b10 i
0,
b11 d
b10 A
b10 Q
b10 b
b1010 P
b10 T
b10 N
b0 O
b1010 R
b1010 I
b1111111111110111 E
b1010 F
b0 G
1-
b1000000000001100 8
b10 H
b1010 V
b10000 M
b10 L
b1010 U
b1010 S
b10 3
b10 D
b10 4
b10 n
b1000 5
b1000 X
b1000 o
0?
b10000 1
b10000 W
b10000 h
b10000 m
b0 +
b0 J
b0 Y
b11 6
b11 K
b11 Z
07
0'
b10 2
b10 @
b10 `
b10 /
b10 \
b10 k
b1 0
b1 ]
b1 j
b0 .
b0 [
b0 l
09
0<
0:
0>
b11 ^
b11000100000010 =
b11000100000010 _
b11000100000010 g
0#
b11000100000010 $
b11000100000010 (
b11000100000010 c
#95000
bx d
bx A
bx Q
bx b
bx P
bx N
bx T
bx H
bx 3
bx D
bx R
b0x O
bx I
b111111111111x1x1 E
bx F
b0x0x0 G
x'
x,
b0x0x0 4
b0x0x0 n
bx S
bx U
bx L
bx M
bx V
b0x0x0 5
b0x0x0 X
b0x0x0 o
x?
bx +
bx J
bx Y
bx 6
bx K
bx Z
x-
x7
bx *
bx i
bx 8
bx 2
bx @
bx `
bx /
bx \
bx k
bx 0
bx ]
bx j
bx .
bx [
bx l
x9
x<
x:
x>
bx ^
b0x0x0 1
b0x0x0 W
b0x0x0 h
b0x0x0 m
b1000000000001101 e
bx =
bx _
bx g
b1000000000001100 C
b1000000000001100 a
b100 r
1#
#100000
b0 *
b0 i
b1 d
b0 A
b0 Q
b0 b
0,
b0 P
b1010 T
b1010 N
b0 O
b0 R
b1010 I
b1111111111110111 E
b1010 F
b0 G
1-
b1000000000001110 8
b10 H
b1010 V
b10000 M
b10 L
b1010 U
b1010 S
b10 3
b10 D
b10 4
b10 n
b1000 5
b1000 X
b1000 o
0?
b10 1
b10 W
b10 h
b10 m
b1 +
b1 J
b1 Y
b0 6
b0 K
b0 Z
07
0'
b10 2
b10 @
b10 `
b10 /
b10 \
b10 k
b1 0
b1 ]
b1 j
b0 .
b0 [
b0 l
09
0<
0:
0>
b100 ^
b100000100000010 =
b100000100000010 _
b100000100000010 g
0#
b100000100000010 $
b100000100000010 (
b100000100000010 c
#105000
bx d
bx A
bx Q
bx b
bx R
bx P
bx H
bx 3
bx D
b0x O
bx N
bx T
bx I
b111111111111x1x1 E
bx F
b0x0x0 G
x,
b0x0x0 4
b0x0x0 n
bx S
bx U
bx L
bx M
bx V
b0x0x0 5
b0x0x0 X
b0x0x0 o
bx +
bx J
bx Y
bx 6
bx K
bx Z
x-
x7
bx *
bx i
x'
x?
b0x0x0 1
b0x0x0 W
b0x0x0 h
b0x0x0 m
bx 8
bx 2
bx @
bx `
bx /
bx \
bx k
bx 0
bx ]
bx j
bx .
bx [
bx l
x9
x<
x:
x>
bx ^
b1000000000001111 e
bx =
bx _
bx g
b1000000000001110 C
b1000000000001110 a
b100 r
1#
#110000
b1010 *
b1010 i
b1011 d
b1010 A
b1010 Q
b1010 b
0,
b1010 P
b1010 T
b1010 N
b0 O
b0 R
b1010 I
b1111111111110111 E
b1010 F
b0 G
1-
b1000000000010000 8
b10 H
b1010 V
b10000 M
b10 L
b1010 U
b1010 S
b10 3
b10 D
b10 4
b10 n
b1000 5
b1000 X
b1000 o
1?
b0 1
b0 W
b0 h
b0 m
b1 +
b1 J
b1 Y
b1 6
b1 K
b1 Z
07
0'
b10 2
b10 @
b10 `
b10 /
b10 \
b10 k
b1 0
b1 ]
b1 j
b0 .
b0 [
b0 l
09
0<
0:
0>
b101 ^
b101000100000010 =
b101000100000010 _
b101000100000010 g
0#
b101000100000010 $
b101000100000010 (
b101000100000010 c
#115000
bx P
bx d
bx A
bx Q
bx b
bx R
bx H
bx 3
bx D
b0x O
bx N
bx T
bx I
b111111111111x1x1 E
bx F
b0x0x0 G
x'
x,
b0x0x0 4
b0x0x0 n
bx S
bx U
bx L
bx M
bx V
b0x0x0 5
b0x0x0 X
b0x0x0 o
bx +
bx J
bx Y
bx 6
bx K
bx Z
x-
x7
bx *
bx i
bx 8
bx 2
bx @
bx `
bx /
bx \
bx k
bx 0
bx ]
bx j
bx .
bx [
bx l
x9
x<
x:
x>
bx ^
x?
b0x0x0 1
b0x0x0 W
b0x0x0 h
b0x0x0 m
b1000000000010001 e
bx =
bx _
bx g
b1000000000010000 C
b1000000000010000 a
b100 r
1#
#120000
b1010000 T
b1111111111110111 *
b1111111111110111 i
b1 O
b10010 R
b1111111111111000 d
b1111111111110111 A
b1111111111110111 Q
b1111111111110111 b
b10010 V
b1010000 M
b0 L
b10010 U
b10010 S
0,
b1111111111110111 P
b1010 N
b10 I
b1111111111110111 E
b1010 F
b1000 G
1-
b1000000000010010 8
b1010 H
b1010 3
b1010 D
b1010 4
b1010 n
b1000 5
b1000 X
b1000 o
0?
b1010 1
b1010 W
b1010 h
b1010 m
b1 +
b1 J
b1 Y
b10 6
b10 K
b10 Z
07
0'
b0 2
b0 @
b0 `
b0 /
b0 \
b0 k
b1 0
b1 ]
b1 j
b0 .
b0 [
b0 l
09
0<
0:
0>
b110 ^
b110000100000000 =
b110000100000000 _
b110000100000000 g
0#
b110000100000000 $
b110000100000000 (
b110000100000000 c
#125000
bx d
bx A
bx Q
bx b
bx P
bx T
bx N
bx R
b0x O
bx I
bx E
bx F
bx G
x,
bx H
bx 3
bx D
bx S
bx U
bx L
bx M
bx V
bx 5
bx X
bx o
bx +
bx J
bx Y
bx 6
bx K
bx Z
x-
x7
bx *
bx i
x'
bx 4
bx n
x?
bx 1
bx W
bx h
bx m
bx 8
bx 2
bx @
bx `
bx /
bx \
bx k
bx 0
bx ]
bx j
bx .
bx [
bx l
x9
x<
x:
x>
bx ^
b1000000000010011 e
bx =
bx _
bx g
b1000000000010010 C
b1000000000010010 a
b100 r
1#
#130000
b1010 *
b1010 i
b1011 d
b1010 A
b1010 Q
b1010 b
0,
b1010 P
b10 T
b10 N
b0 O
b1010 R
b1010 I
b1111111111110111 E
b1010 F
b0 G
1-
b1000000000010100 8
b10 H
b1010 V
b10000 M
b10 L
b1010 U
b1010 S
b10 3
b10 D
b10 4
b10 n
b1000 5
b1000 X
b1000 o
0?
b1111111111110111 1
b1111111111110111 W
b1111111111110111 h
b1111111111110111 m
b1 +
b1 J
b1 Y
b11 6
b11 K
b11 Z
07
0'
b10 2
b10 @
b10 `
b10 /
b10 \
b10 k
b1 0
b1 ]
b1 j
b0 .
b0 [
b0 l
09
0<
0:
0>
b111 ^
b111000100000010 =
b111000100000010 _
b111000100000010 g
0#
b111000100000010 $
b111000100000010 (
b111000100000010 c
#135000
bx d
bx A
bx Q
bx b
bx P
bx N
bx T
bx H
bx 3
bx D
bx R
b0x O
bx I
b111111111111x1x1 E
bx F
b0x0x0 G
x'
x,
b0x0x0 4
b0x0x0 n
bx S
bx U
bx L
bx M
bx V
b0x0x0 5
b0x0x0 X
b0x0x0 o
x?
bx +
bx J
bx Y
bx 6
bx K
bx Z
x-
x7
bx *
bx i
bx 8
bx 2
bx @
bx `
bx /
bx \
bx k
bx 0
bx ]
bx j
bx .
bx [
bx l
x9
x<
x:
x>
bx ^
b0x0x0 1
b0x0x0 W
b0x0x0 h
b0x0x0 m
b1000000000010101 e
bx =
bx _
bx g
b1000000000010100 C
b1000000000010100 a
b100 r
1#
